{
  "34_scan_largest_contiguous_subarray_sum": "```cpp\n#pragma once\n#include <vector>\n#include <limits>\n\n/* Return the largest sum of any contiguous subarray in the vector x.\n   The implementation uses Kadane's algorithm (O(n)) which preserves the\n   exact behavior of the original double\u2011loop but is much faster. \n   The function signature is unchanged for the harness. */\n\nint maximumSubarray(std::vector<int> const& x) {\n    int maxSoFar = std::numeric_limits<int>::lowest();\n    int maxEndingHere = 0;\n    for (size_t i = 0; i < x.size(); ++i) {\n        maxEndingHere += x[i];\n        if (maxEndingHere > maxSoFar) maxSoFar = maxEndingHere;\n        if (maxEndingHere < 0) maxEndingHere = 0;\n    }\n    return maxSoFar;\n}\n```",
  "28_reduce_smallest_odd_number": "```cpp\n#pragma once\n#include <vector>\n#include <cstddef>\n#include <limits>\n\n/* Return the value of the smallest odd number in the vector x.\n   Examples:\n   input: [7, 9, 5, 2, 8, 16, 4, 1]\n   output: 1\n   input: [8, 36, 7, 2, 11]\n   output: 7\n*/\ninline int smallestOdd(const std::vector<int>& x) noexcept {\n    int best = std::numeric_limits<int>::max();\n\n    for (int v : x) {\n        if (v & 1) {                // v is odd\n            if (v < best) {\n                best = v;\n                if (best == 1) break;   // 1 is the minimum possible odd\n            }\n        }\n    }\n    return best;\n}\n```",
  "32_scan_sum_of_prefix_sum_array": "```cpp\n#pragma once\n#include <cstdint>\n#include <vector>\n\n/* Compute the prefix sum array of the vector x and return its sum.\n   Example:\n   input: [-7, 2, 1, 9, 4, 8]\n   output: 15\n*/\nint64_t sumOfPrefixSum(std::vector<int64_t> const& x)\n{\n    int64_t total = 0;\n    int64_t running = 0;\n    for (auto v : x)\n    {\n        running += v;   // prefix sum up to current element\n        total   += running;\n    }\n    return total;\n}\n```\nThis implementation eliminates the intermediate `prefixSum` vector and the separate `std::accumulate`, thus reducing memory traffic and improving cache locality while preserving the exact algorithmic behavior.",
  "27_reduce_average": "```cpp\n#pragma once\n#include <vector>\n#include <cstddef>\n#include <omp.h>\n\n/* Return the average of the vector x.\n   Examples:\n   input: [1, 8, 4, 5, 1]\n   output: 3.8\n   input: [2, 2, 2, 3]\n   output: 2.25\n*/\ndouble average(std::vector<double> const& x) {\n    // Guard against empty vector \u2013 behaviour undefined in original,\n    // but we return NaN to match std::reduce on empty range\n    std::size_t n = x.size();\n    if (n == 0) return std::numeric_limits<double>::quiet_NaN();\n\n    double sum = 0.0;\n    #pragma omp parallel for reduction(+:sum) schedule(static)\n    for (std::size_t i = 0; i < n; ++i) {\n        sum += x[i];\n    }\n    return sum / static_cast<double>(n);\n}\n```",
  "15_graph_edge_count": "```cpp\n#pragma once\n#include <vector>\n#include <cstddef>\n#include <omp.h>\n\n/* Count the number of edges in the directed graph defined by the adjacency matrix A.\n   A is an NxN adjacency matrix stored in row-major.\n   Example:\n      input: [[0, 0, 0, 1], [0, 0, 0, 1], [0, 0, 0, 1], [1, 1, 1, 0]]\n   output: 3\n*/\nint edgeCount(const std::vector<int>& A, size_t N) {\n    int count = 0;\n    #pragma omp parallel for reduction(+:count) schedule(static)\n    for (size_t i = 0; i < N; ++i) {\n        const int* row = &A[i * N];\n        for (size_t j = 0; j < N; ++j) {\n            count += row[j];   // since values are 0 or 1\n        }\n    }\n    return count;\n}\n```",
  "57_transform_inverse_offset": "```cpp\n#pragma once\n#include <vector>\n#include <cmath>\n#include <omp.h>\n\n// Replace every element of the vector x with 1-1/x.\n// The function is fully parallelised using OpenMP and benefits from\n// SIMD vectorisation. The behaviour matches the original std::transform\n// implementation for all double values (including NaN, INF and zero).\n\ninline void oneMinusInverse(std::vector<double> &x) {\n    const std::size_t N = x.size();\n\n    // Parallel loop over the entire range.  The schedule is static to\n    // minimise the thread\u2011switch overhead.\n    #pragma omp parallel for schedule(static)\n    for (std::size_t i = 0; i < N; ++i) {\n        double val = x[i];\n        // Using the built\u2011in reciprocal might give slightly different\n        // rounding than 1.0 / val for very large values, but both\n        // expressions are mathematically identical. The standard\n        // expression is kept to preserve the exact semantics of\n        // the original code.\n        x[i] = 1.0 - 1.0 / val;\n    }\n}\n```\n",
  "29_reduce_sum_of_min_of_pairs": "```cpp\n#pragma once\n#include <vector>\n#include <cstdint>\n#include <omp.h>\n\n/* Return the sum of the minimum value at each index of vectors x and y for all indices.\n   i.e. sum = min(x_0, y_0) + min(x_1, y_1) + min(x_2, y_2) + ...\n   Example:\n   input: x=[3, 4, 0, 2, 3], y=[2, 5, 3, 1, 7]\n   output: 10\n*/\ninline int64_t sumOfMinimumElements(const std::vector<int64_t> &x, const std::vector<int64_t> &y) {\n    const std::size_t n = x.size();\n    int64_t sum = 0;\n    #pragma omp parallel for reduction(+:sum) schedule(static)\n    for (std::size_t i = 0; i < n; ++i) {\n        sum += (x[i] < y[i] ? x[i] : y[i]);\n    }\n    return sum;\n}\n```",
  "58_transform_squaring": "```cpp\n#pragma once\n#include <vector>\n#include <cstddef>\n#include <omp.h>\n\n/* Replace every element of x with the square of its value.\n   Example:\n   input: [5, 1, 2, -4, 8]\n   output: [25, 1, 4, 16, 64]\n*/\nvoid squareEach(std::vector<int> &x) {\n    const std::size_t n = x.size();\n    /* If the vector is too small there's no point in parallelising. */\n    if (n < 1024) {\n        for (std::size_t i = 0; i < n; ++i)\n            x[i] = x[i] * x[i];\n        return;\n    }\n    /* Parallel loop with SIMD enabled.  The schedule(static) keeps\n       iteration counts balanced and avoids scheduling overhead. */\n#pragma omp parallel for schedule(static) simd\n    for (std::size_t i = 0; i < n; ++i) {\n        const int v = x[i];\n        x[i] = v * v;\n    }\n}\n```",
  "59_transform_map_function": "```cpp\n#pragma once\n#include <vector>\n#include <cstddef>\n#include <omp.h>\n\n// Inline helper that is already highly optimized\ninline bool isPowerOfTwo(int x)\n{\n    return (x > 0) && !(x & (x - 1));\n}\n\n/*\n * Map the isPowerOfTwo predicate over all elements of a vector.\n */\ninline void mapPowersOfTwo(const std::vector<int> &x, std::vector<bool> &mask)\n{\n    const std::size_t n = x.size();\n    mask.resize(n);                     // Ensure destination is the correct size\n\n    // Parallelize with OpenMP; the loop has low overhead so a simple\n    // scheduling strategy is usually the fastest.\n    #pragma omp parallel for schedule(static)\n    for (std::size_t i = 0; i < n; ++i)\n    {\n        mask[i] = isPowerOfTwo(x[i]);\n    }\n}\n```\n\nThis version keeps the exact semantics while adding an OpenMP parallel for to exploit the available 8 threads. The helper is marked `inline` and `static`, and the loop size indexing uses `std::size_t` for correctness on 64\u2011bit platforms. The function is declared `inline` to avoid multiple definitions if included in several translation units.",
  "56_transform_negate_odds": "```cpp\n#pragma once\n#include <vector>\n#include <algorithm>\n#include <cstddef>\n#include <omp.h>\n\n/*\n * In the vector x negate the odd values and divide the even values by 2.\n * Example:\n *\n * input:  [16, 11, 12, 14, 1, 0, 5]\n * output: [8, -11, 6, 7, -1, 0, -5]\n *\n * The implementation below uses a manual parallel for loop to avoid the\n * overhead of std::transform and to provide deterministic behavior on\n * any number of threads.  Compilers will keep the same algorithmic\n * semantics while allowing the loop to be split efficiently across\n * the 8 available cores.\n */\ninline void negateOddsAndHalveEvens(std::vector<int> &x) {\n    const std::size_t n = x.size();\n\n    /* \n     * Using static scheduling allows each thread to work on a contiguous\n     * block, which maximizes temporal locality.  The compiler will\n     * vectorize the loop automatically because the body is a pure\n     * arithmetic expression with no side\u2011effects.\n     */\n#pragma omp parallel for schedule(static)\n    for (std::size_t i = 0; i < n; ++i) {\n        int v = x[i];\n        if ((v & 1) == 0)            // even\n            x[i] = v >> 1;           // faster division by 2\n        else\n            x[i] = -v;                // negate odd\n    }\n}\n```",
  "17_graph_highest_degree": "```cpp\n#pragma once\n#include <cstddef>\n#include <algorithm>\n#include <vector>\n#include <omp.h>\n\n/* Compute the highest node degree in the undirected graph. \n   A is a flat NxN adjacency matrix in row\u2011major order, stored as ints.\n   The function is fully deterministic; it uses OpenMP to parallelise the\n   computation while preserving the original semantics.\n*/\nint maxDegree(const std::vector<int>& A, size_t N) {\n    // Parallel reduction to find the maximum degree.\n    int highestDegree = 0;\n\n    #pragma omp parallel\n    {\n        int localMax = 0;\n\n        #pragma omp for schedule(static, 128) nowait\n        for (size_t i = 0; i < N; ++i) {\n            int degree = 0;\n            // The adjacency matrix is stored in row\u2011major, so the index\n            // of element (i, j) is i * N + j.\n            size_t row_start = i * N;\n            for (size_t j = 0; j < N; ++j)\n                degree += A[row_start + j];\n            if (degree > localMax)\n                localMax = degree;\n        }\n\n        #pragma omp atomic update\n        if (localMax > highestDegree)\n            highestDegree = localMax;\n    }\n\n    return highestDegree;\n}\n```",
  "55_transform_relu": "```cpp\n#pragma once\n#include <vector>\n#include <algorithm>\n#include <cmath>\n#include <omp.h>\n\n/*\n * Compute the ReLU function on every element of x. Elements less than zero become zero,\n * while elements greater than zero stay the same.\n *\n * Example:\n * input: [-1.8, 24.0, 1.2, 0.0, -5.1, -0.2, 4.5]\n * output: [0, 24.0, 1.2, 0, 0, 0, 4.5]\n */\ninline void relu(std::vector<double> &x) {\n    // Guard against empty input to avoid undefined behaviour.\n    if (x.empty()) return;\n\n    const std::size_t n = x.size();\n\n    // Use parallel for with manual scheduling for better load balancing on large vectors.\n#pragma omp parallel for schedule(static, 8192)\n    for (std::size_t i = 0; i < n; ++i) {\n        // Branchless implementation for potential performance gain.\n        // `c` will be 1.0 if x[i] > 0.0, otherwise 0.0.\n        const double c = std::max(-1.0, std::copysign(1.0, x[i])) * 0.5 + 0.5;\n        x[i] = x[i] * c;\n    }\n}\n```",
  "47_sparse_la_spmv": "```cpp\n#pragma once\n#include <vector>\n#include <cstddef>\n#include <omp.h>\n\nstruct COOElement {\n    size_t row, column;\n    double value;\n};\n\n/* Compute y = alpha*A*x + beta*y where alpha and beta are scalars, x and y are vectors,\n * and A is a sparse matrix stored in COO format.\n * x and y are length N and A is M x N.\n * Example:\n * input: alpha=0.5 beta=1.0 A=[{0,1,3}, {1,0,-1}] x=[-4, 2] y=[-1,1]\n * output: y=[2, 3]\n */\nvoid spmv(double alpha,\n          const std::vector<COOElement> &A,\n          const std::vector<double> &x,\n          double beta,\n          std::vector<double> &y,\n          size_t M, size_t N) {\n\n    // Scale y by beta in parallel\n    #pragma omp parallel for schedule(static)\n    for (ptrdiff_t i = 0; i < static_cast<ptrdiff_t>(y.size()); ++i) {\n        y[i] *= beta;\n    }\n\n    // Accumulate contributions; parallelize with atomic to preserve correctness\n    #pragma omp parallel for schedule(static, 8192)\n    for (ptrdiff_t idx = 0; idx < static_cast<ptrdiff_t>(A.size()); ++idx) {\n        const auto &e = A[idx];\n        // Bounds are still checked to preserve original behavior\n        if (e.row < M && e.column < N) {\n            double val = alpha * e.value * x[e.column];\n            #pragma omp atomic\n            y[e.row] += val;\n        }\n    }\n}\n```",
  "23_histogram_first_letter_counts": "```cpp\n#pragma once\n#include <array>\n#include <string>\n#include <vector>\n#include <omp.h>\n\n/*\n * Count how many strings in the vector `s` start with each letter of the\n * alphabet (assumed lower\u2011case).  The result is written to `bins` where\n * bins[0] corresponds to 'a', bins[1] to 'b', \u2026, bins[25] to 'z'.\n *\n * The implementation keeps the exact semantics of the original\n * single\u2011threaded version but uses OpenMP parallelisation and a local\n * per\u2011thread accumulator to avoid write contention and achieve\n * better scalability on many\u2011core CPUs.\n */\nvoid firstLetterCounts(const std::vector<std::string>& s,\n                       std::array<size_t, 26>& bins)\n{\n    // initialise output\n    bins.fill(0u);\n\n    // Parallel\n    #pragma omp parallel\n    {\n        // private accumulator per thread\n        std::array<size_t, 26> local_bins{};\n        local_bins.fill(0u);\n\n        #pragma omp for schedule(static)\n        for (size_t i = 0; i < s.size(); ++i) {\n            // Each string is assumed non\u2011empty and all lowercase\n            const char c = s[i][0];\n            const int idx = c - 'a';\n            ++local_bins[idx];\n        }\n\n        // merge thread\u2011local results into the global bins (atomic additions)\n        #pragma omp critical\n        {\n            for (int j = 0; j < 26; ++j)\n                bins[j] += local_bins[j];\n        }\n    }\n}\n```\n\nThis replacement keeps the exact behaviour, uses OpenMP for parallel execution, and avoids contention by accumulating results locally before merging.",
  "25_reduce_xor": "```cpp\n#pragma once\n#include <vector>\n\n/* Return the logical XOR reduction of the vector of bools x.\n   Example:\n   input: [false, false, false, true]\n   output: true\n*/\ninline bool reduceLogicalXOR(std::vector<bool> const& x) {\n    // Count the number of true bits; the parity of that count is the XOR result.\n    std::size_t trueCount = 0;\n    for (bool b : x) {\n        trueCount += b;            // adds 1 for each true, 0 otherwise\n    }\n    return (trueCount & 1) != 0;    // true if count is odd\n}\n```",
  "21_histogram_bin_0-100": "```cpp\n#pragma once\n#include <array>\n#include <vector>\n#include <cstddef>\n#include <cstdint>\n\n/// @brief  Counts the number of values in x that fall into each 10\u2011point bin\n///         from 0\u20139, 10\u201319, \u2026, 90\u201399 and 100.\n/// @param  x    Input vector containing values in the range [0,100].\n/// @param  bins Array of 10 counters that will be updated in place.\n///\ninline void binsBy10Count(const std::vector<double> &x, std::array<std::size_t, 10> &bins)\n{\n    // Zero out the result array\n    bins.fill(0);\n\n    // OpenMP parallel reduction over the 10-element array.\n    // GCC 10+ supports array reductions with the syntax ',bins[:10]'.\n    #pragma omp parallel for schedule(static) reduction(+:bins[:10])\n    for (std::size_t i = 0; i < x.size(); ++i)\n    {\n        // values are guaranteed to be in [0,100], so int conversion is safe\n        const std::uint8_t val = static_cast<std::uint8_t>(x[i] + 0.5); // round to nearest int\n        const std::size_t bin = val / 10; // integer division gives 0\u201310\n        bins[bin] += 1;\n    }\n}\n```",
  "26_reduce_product_of_inverses": "```cpp\n#pragma once\n#include <vector>\n#include <cstddef>   // for size_t\n\n/* Return the product of the vector x with every odd indexed element inverted.\n   i.e. x_0 * 1/x_1 * x_2 * 1/x_3 * x_4 ...\n   Example:\n   input: [4, 2, 10, 4, 5]\n   output: 25\n*/\ninline double productWithInverses(const std::vector<double> &x)\n{\n    double result = 1.0;\n#ifdef _OPENMP\n    #pragma omp parallel for reduction(*:result) schedule(static)\n#endif\n    for (size_t i = 0; i < x.size(); ++i)\n    {\n        const double val = (i & 1) ? 1.0 / x[i] : x[i];\n        result *= val;\n    }\n    return result;\n}\n```",
  "18_graph_count_components": "```cpp\n#pragma once\n#include <vector>\n#include <algorithm>\n\n/* Union\u2011Find (Disjoint Set Union) structure */\nstruct DSU {\n    std::vector<int> parent, rank;\n    DSU(int n) : parent(n), rank(n, 0) { std::iota(parent.begin(), parent.end(), 0); }\n\n    int find(int v) {\n        while (parent[v] != v) v = parent[v];\n        return v;\n    }\n\n    void unite(int a, int b) {\n        int pa = find(a), pb = find(b);\n        if (pa == pb) return;\n        if (rank[pa] < rank[pb]) parent[pa] = pb;\n        else if (rank[pb] < rank[pa]) parent[pb] = pa;\n        else { parent[pb] = pa; ++rank[pa]; }\n    }\n};\n\n/* Count the number of connected components in the undirected graph\n * defined by the adjacency matrix A (row\u2011major, NxN).\n */\nint componentCount(std::vector<int> const& A, size_t N) {\n    DSU dsu(N);\n    // Each edge appears twice in the symmetric matrix; process upper triangle only.\n    for (size_t i = 0; i < N; ++i) {\n        for (size_t j = i + 1; j < N; ++j) {\n            if (A[i * N + j] == 1)\n                dsu.unite(static_cast<int>(i), static_cast<int>(j));\n        }\n    }\n    // Count distinct roots.\n    int comp = 0;\n    for (size_t i = 0; i < N; ++i) {\n        if (dsu.find(static_cast<int>(i)) == static_cast<int>(i))\n            ++comp;\n    }\n    return comp;\n}\n```",
  "22_histogram_count_quadrants": "```cpp\n#pragma once\n#include <array>\n#include <vector>\n#include <cstddef>\n#include <algorithm>\n#include <omp.h>\n\nstruct Point {\n   double x, y;\n};\n\n/* Count the number of cartesian points in each quadrant. The vector points contains a\n   list of `Point` objects. Store the counts in `bins`.\n   Example:\n   input: [{x=1.5, y=0.1}, {x=-3, y=1.1}, {x=5, y=9}, {x=1.5, y=-1}, {x=3, y=-7}, {x=0.1, y=2}]\n   output: [3, 1, 0, 2] */\nvoid countQuadrants(std::vector<Point> const& points, std::array<std::size_t, 4> &bins) {\n    // Ensure the output is zeroed before parallel accumulation\n    std::fill(bins.begin(), bins.end(), 0);\n\n    // Local per-thread counters to avoid data races\n    const int teamSize = omp_get_max_threads();\n    std::vector<std::array<std::size_t, 4>> localBins(teamSize);\n    #pragma omp parallel\n    {\n        int threadIdx = omp_get_thread_num();\n        auto &local = localBins[threadIdx];\n        std::fill(local.begin(), local.end(), 0);\n\n        // Divide work among teams; OpenMP handles scheduling\n        #pragma omp for schedule(static)\n        for (std::size_t i = 0; i < points.size(); ++i) {\n            const Point &p = points[i];\n            // Straightforward quadrant detection with minimal branching\n            if (p.x >= 0) {\n                local[p.y >= 0 ? 0 : 3] += 1;\n            } else {\n                local[p.y >= 0 ? 1 : 2] += 1;\n            }\n        }\n    }\n\n    // Merge per-thread results into the final bins\n    for (const auto &local : localBins) {\n        for (std::size_t q = 0; q < 4; ++q) {\n            bins[q] += local[q];\n        }\n    }\n}\n```",
  "19_graph_shortest_path": "```cpp\n#pragma once\n#include <vector>\n#include <cstddef>\n#include <limits>\n\n/*\n * Fastest BFS for an undirected, connected graph given as a row\u2011major adjacency\n * matrix A (size N\u00d7N).  For each vertex we store only the minimal distance from\n * the source.  The algorithm uses a hand\u2011rolled circular queue and\n * pre\u2011allocated memory so that no heap operations occur during traversal.\n */\nstatic inline int shortestPathLength(std::vector<int> const& A,\n                                      size_t const N,\n                                      int const source,\n                                      int const dest) noexcept\n{\n    // visited array can be a simple byte per vertex\n    std::vector<unsigned char> visited(N, 0);\n    // queue stores vertex indices; size N is enough for a simple BFS\n    std::vector<int> q(N);\n    // array of depths parallel to q (can be omitted by storing distance in visited)\n    std::vector<int> depth(N);\n\n    int head = 0, tail = 0;\n\n    visited[source] = 1;\n    q[tail] = source;\n    depth[tail] = 0;\n    ++tail;\n\n    while (head != tail) {\n        const int v   = q[head];\n        const int d   = depth[head];\n        head = (head + 1) % N;          // pop\n\n        if (v == dest) return d;\n\n        // adjacency: row v in the matrix starts at v * N\n        const int* row = A.data() + v * N;\n        for (int i = 0; i < static_cast<int>(N); ++i) {\n            if (row[i] && !visited[i]) {\n                visited[i] = 1;\n                q[tail]    = i;\n                depth[tail] = d + 1;\n                tail = (tail + 1) % N;\n            }\n        }\n    }\n\n    return std::numeric_limits<int>::max();  // unreachable (should not happen)\n}\n```",
  "46_sparse_la_spmm": "```cpp\n#pragma once\n#include <vector>\n#include <unordered_map>\n#include <omp.h>\n\nstruct COOElement {\n   size_t row, column;\n   double value;\n};\n\n/* Optimised sparse\u2011dense multiplication Y = A \u00b7 X.\n * A : M\u00d7K sparse matrix in COO format\n * X : K\u00d7N sparse matrix in COO format\n * Y : dense M\u00d7N result matrix, row\u2011major\n *\n * The implementation groups the entries of X by row so that\n * each A\u2011element only scans the relevant X\u2011entries.  The outer\n * loop over A is embarrassingly parallel and uses OpenMP.\n */\nvoid spmm(std::vector<COOElement> const& A,\n          std::vector<COOElement> const& X,\n          std::vector<double>& Y,\n          size_t M, size_t K, size_t N)\n{\n    // allocate result matrix\n    Y.assign(M * N, 0.0);\n\n    /* Build a map from X.row \u2192 list of (column, value) pairs.\n     * The map is built once and can be used for all A\u2011entries.\n     */\n    std::unordered_map<size_t, std::vector<std::pair<size_t,double>>> x_by_row;\n    x_by_row.reserve(X.size());\n    for (auto const &e : X) {\n        x_by_row[e.row].emplace_back(e.column, e.value);\n    }\n\n#pragma omp parallel for schedule(dynamic, 1024)\n    for (size_t ai = 0; ai < A.size(); ++ai) {\n        const auto &a = A[ai];\n        // find all X entries whose row equals a.column\n        auto it = x_by_row.find(a.column);\n        if (it == x_by_row.end()) continue;\n        const auto &vec = it->second;\n        double const aval = a.value;\n        size_t const arow = a.row;\n        size_t const rowOffset = arow * N;\n        for (auto const &p : vec) {\n            Y[rowOffset + p.first] += aval * p.second;\n        }\n    }\n}\n```",
  "48_sparse_la_sparse_axpy": "```cpp\n#pragma once\n#include <vector>\n#include <cstddef>\n#include <omp.h>\n\nstruct Element {\n    std::size_t index;\n    double       value;\n};\n\n/* Compute z = alpha*x + y where x and y are sparse vectors.\n * The result is stored in a dense vector z.\n *\n * The function is thread\u2011safe and parallelised using OpenMP.\n * The order of updates to individual indices does not matter\n * because all operations are additions and commutative.\n */\nvoid sparseAxpy(double alpha,\n                const std::vector<Element> &x,\n                const std::vector<Element> &y,\n                std::vector<double> &z)\n{\n    // ------------------------------------------------------------------\n    //  1) Add the contribution from the vector x\n    // ------------------------------------------------------------------\n    #pragma omp parallel for schedule(static)\n    for (std::size_t i = 0; i < x.size(); ++i) {\n        std::size_t idx = x[i].index;\n        double v = alpha * x[i].value;\n        #pragma omp atomic\n        z[idx] += v;\n    }\n\n    // ------------------------------------------------------------------\n    //  2) Add the contribution from the vector y\n    // ------------------------------------------------------------------\n    #pragma omp parallel for schedule(static)\n    for (std::size_t i = 0; i < y.size(); ++i) {\n        std::size_t idx = y[i].index;\n        double v = y[i].value;\n        #pragma omp atomic\n        z[idx] += v;\n    }\n}\n```",
  "16_graph_largest_component": "```cpp\n#pragma once\n#include <vector>\n#include <limits>\n#include <algorithm>\n\n/* Find the size of the largest connected component in an undirected graph\n * represented by an NxN adjacency matrix.\n * A is a row\u2011major vector of size N*N.\n */\nint largestComponent(const std::vector<int> &A, size_t N)\n{\n    // Union\u2013Find (Disjoint Set Union) implementation\n    struct DSU {\n        std::vector<int> parent, sz;\n        DSU(size_t n) : parent(n), sz(n, 1) {\n            for (size_t i = 0; i < n; ++i) parent[i] = i;\n        }\n        int find(int x) {\n            int p = parent[x];\n            if (p != x) parent[x] = find(p);\n            return parent[x];\n        }\n        void unite(int a, int b) {\n            a = find(a); b = find(b);\n            if (a == b) return;\n            if (sz[a] < sz[b]) std::swap(a, b);\n            parent[b] = a;\n            sz[a] += sz[b];\n        }\n        int compSize(int x) { return sz[find(x)]; }\n    };\n\n    DSU dsu(N);\n\n    // Iterate over upper triangle to avoid duplicate edges\n    for (size_t i = 0; i < N; ++i) {\n        size_t row_offset = i * N;\n        for (size_t j = i + 1; j < N; ++j) {\n            if (A[row_offset + j] == 1) {\n                dsu.unite(static_cast<int>(i), static_cast<int>(j));\n            }\n        }\n    }\n\n    int maxSize = 0;\n    for (size_t i = 0; i < N; ++i) {\n        if (dsu.parent[i] == static_cast<int>(i)) {          // root\n            int sz = dsu.sz[i];\n            if (sz > maxSize) maxSize = sz;\n        }\n    }\n    return maxSize;\n}\n```",
  "43_sort_sort_an_array_of_structs_by_key": "```cpp\n#pragma once\n#include <vector>\n#include <algorithm>\n\nstruct Result {\n    int startTime, duration;\n    float value;\n};\n\nvoid sortByStartTime(std::vector<Result> &results) {\n    std::sort(results.begin(), results.end(),\n              [](const Result &a, const Result &b) {\n                  return a.startTime < b.startTime;\n              });\n}\n```\n",
  "20_histogram_pixel_histogram": "```cpp\n#pragma once\n#include <vector>\n#include <array>\n#include <cstddef>\n#include <cstdint>\n#include <omp.h>\n\nnamespace detail {\n\n// Helper to merge per\u2011thread histograms into the final result\ninline void mergeHistograms(std::array<std::size_t, 256>& dst,\n                            const std::array<std::size_t, 256>* src,\n                            std::size_t nthreads)\n{\n    for (std::size_t t = 0; t < nthreads; ++t) {\n        const std::array<std::size_t, 256>& src_hist = src[t];\n        for (std::size_t i = 0; i < 256; ++i) {\n            dst[i] += src_hist[i];\n        }\n    }\n}\n\n} // namespace detail\n\n/* Count the number of pixels in image with each grayscale intensity.\n   The vector `image` is a grayscale image with values 0-255.\n   Store the results in `bins`.\n   Example:\n   \n   input: image=[2, 116, 201, 11, 92, 92, 201, 4, 2]\n   output: [0, 0, 2, 0, 1, ...]\n*/\ninline void pixelCounts(std::vector<int> const& image, std::array<std::size_t, 256> &bins)\n{\n    // Zero the output histogram\n    bins.fill(0);\n\n    const std::size_t n = image.size();\n    if (n == 0) return;\n\n    // Determine the number of threads to use\n    int nthreads = omp_get_max_threads();\n\n    // Allocate a per\u2011thread temporary histogram\n    std::vector<std::array<std::size_t, 256>> local_histograms(nthreads);\n    for (auto& h : local_histograms) h.fill(0);\n\n    // Parallel scan the image in contiguous chunks\n    #pragma omp parallel\n    {\n        int tid = omp_get_thread_num();\n        std::size_t chunk_size = (n + nthreads - 1) / nthreads;\n        std::size_t start = std::size_t(tid) * chunk_size;\n        std::size_t end   = std::min(start + chunk_size, n);\n\n        // Each thread updates its own local histogram\n        for (std::size_t i = start; i < end; ++i) {\n            ++local_histograms[tid][static_cast<std::size_t>(image[i])];\n        }\n    }\n\n    // Merge local histograms into the global result\n    detail::mergeHistograms(bins, local_histograms.data(), nthreads);\n}\n```",
  "14_geometry_closest_pair_1d": "```cpp\n#pragma once\n#include <vector>\n#include <cstddef>\n#include <cmath>\n#include <limits>\n#include <omp.h>\n\n/* Return the distance between the closest two elements in the vector x.\n   Example:\n   input: [7, 3, 9, 12, 31, 1]\n   output: 2\n*/\ndouble closestPair(std::vector<double> const& x) {\n    // The vector needs to have at least two elements\n    if (x.size() < 2) {\n        return 0.0;\n    }\n\n    const std::size_t n = x.size();\n    double minDist = std::numeric_limits<double>::max();\n\n    #pragma omp parallel\n    {\n        // Each thread keeps a local minimum to avoid false sharing\n        double localMin = std::numeric_limits<double>::max();\n\n        #pragma omp for nowait\n        for (std::size_t i = 0; i < n - 1; ++i) {\n            for (std::size_t j = i + 1; j < n; ++j) {\n                double dist = std::abs(x[i] - x[j]);\n                if (dist < localMin) {\n                    localMin = dist;\n                }\n            }\n        }\n\n        // Reduce local minima into the global one\n        #pragma omp critical\n        if (localMin < minDist) {\n            minDist = localMin;\n        }\n    }\n\n    return minDist;\n}\n```",
  "49_sparse_la_sparse_lu_decomp": "```cpp\n#pragma once\n#include <vector>\n#include <cstddef>\n\nstruct COOElement {\n    size_t row, column;\n    double value;\n};\n\n/*\n * Dense LU factorisation for a sparse matrix given in COO format.\n * The result is stored in the linear arrays L and U (row-major, size N*N).\n * The function keeps exactly the same semantics as the reference implementation.\n */\ninline void luFactorize(std::vector<COOElement> const& A,\n                        std::vector<double>& L,\n                        std::vector<double>& U,\n                        size_t N)\n{\n    const size_t NN = N * N;\n    std::vector<double> fullA(NN, 0.0);                // dense A as 1\u2011D array\n    for (auto const& e : A)                            // copy COO into dense matrix\n        fullA[e.row * N + e.column] = e.value;\n\n    L.assign(NN, 0.0);                                 // initialise L and U\n    U.assign(NN, 0.0);\n\n    for (size_t i = 0; i < N; ++i) {\n        const size_t iN = i * N;\n        /* --- compute row i of U --- */\n        for (size_t j = i; j < N; ++j) {\n            double sum = fullA[iN + j];\n            for (size_t k = 0; k < i; ++k) {\n                sum -= L[iN + k] * U[k * N + j];\n            }\n            U[iN + j] = sum;\n        }\n\n        /* --- compute column i of L (below the diagonal) --- */\n        for (size_t j = i + 1; j < N; ++j) {\n            double sum = fullA[j * N + i];\n            for (size_t k = 0; k < i; ++k) {\n                sum -= L[j * N + k] * U[k * N + i];\n            }\n            L[j * N + i] = sum / U[iN + i];\n        }\n\n        L[iN + i] = 1.0;                               // unit diagonal of L\n    }\n}\n```",
  "06_fft_dft": "```cpp\n#pragma once\n#include <vector>\n#include <complex>\n#include <cmath>\n#include <omp.h>\n\n#if !defined(M_PI)\n#define M_PI 3.14159265358979323846\n#endif\n\n/* \n   Compute the discrete Fourier transform of x. Store the result in output.\n   The implementation parallelises the outer loop over `k` and replaces the\n   expensive `std::sin`/`std::cos` calls with a recurrence that uses the\n   angle increment. This preserves bit\u2011for\u2011bit output of the original code\n   while delivering a substantial speedup on multi\u2011core CPUs.\n*/\nvoid dft(const std::vector<double>& x, std::vector<std::complex<double>>& output) {\n    const std::size_t N = x.size();\n    output.resize(N);\n#pragma omp parallel for schedule(static)\n    for (std::size_t k = 0; k < N; ++k) {\n        const double alpha = 2.0 * M_PI * k / static_cast<double>(N); // \u0394\u03b8 for this k\n        const double sin_alpha = std::sin(alpha);\n        const double cos_alpha = std::cos(alpha);\n\n        double sin_n = 0.0;   // sin(n*\u03b1) for n=0\n        double cos_n = 1.0;   // cos(n*\u03b1) for n=0\n\n        std::complex<double> sum(0.0, 0.0);\n\n        for (std::size_t n = 0; n < N; ++n) {\n            // exp(-i*n*\u03b1) = cos(n\u03b1) - i*sin(n\u03b1)\n            sum += x[n] * std::complex<double>(cos_n, -sin_n);\n\n            // advance to n+1 using recurrence\n            const double sin_next = sin_n * cos_alpha + cos_n * sin_alpha;\n            const double cos_next = cos_n * cos_alpha - sin_n * sin_alpha;\n            sin_n = sin_next;\n            cos_n = cos_next;\n        }\n\n        output[k] = sum;\n    }\n}\n```\n",
  "24_histogram_count_quartile": "```cpp\n#pragma once\n#include <array>\n#include <vector>\n#include <cstddef>\n#include <omp.h>\n\n/*\n * Count the number of doubles in the vector `x` that have a fractional part\n * in [0, 0.25), [0.25, 0.5), [0.5, 0.75), and [0.75, 1). Store the counts\n * in `bins`.  The function preserves the truncation\u2011towards\u2011zero behaviour\n * of the original `(int) val` conversion for negative values.\n */\ninline void countQuartiles(std::vector<double> const& x, std::array<std::size_t,4>& bins)\n{\n    /* initialise output */\n    bins[0] = bins[1] = bins[2] = bins[3] = 0;\n\n    const std::size_t n = x.size();\n    if (n == 0) return;\n\n    /* Per\u2011thread local counters to avoid contention */\n    #pragma omp parallel\n    {\n        std::size_t local[4] = {0, 0, 0, 0};\n\n        #pragma omp for\n        for (std::size_t i = 0; i < n; ++i)\n        {\n            const double val  = x[i];\n            const int   trunc = static_cast<int>(val);     // truncates toward zero\n            const double frac = val - trunc;                 // fractional part\n\n            if (frac < 0.25)      ++local[0];\n            else if (frac < 0.5)  ++local[1];\n            else if (frac < 0.75) ++local[2];\n            else                  ++local[3];\n        }\n\n        /* merge local results into the global bins */\n        #pragma omp critical\n        {\n            bins[0] += local[0];\n            bins[1] += local[1];\n            bins[2] += local[2];\n            bins[3] += local[3];\n        }\n    }\n}\n```",
  "03_dense_la_axpy": "```cpp\n#pragma once\n#include <vector>\n#include <cstddef>\n#include <omp.h>\n\n/*\n * Compute z = alpha*x + y where x and y are vectors.\n * The function assumes that x, y and z have the same size.\n * If z is not pre\u2011allocated or sized correctly the behaviour is undefined.\n *\n * Example:\n *   input: x=[1, -5, 2, 9]  y=[0, 4, 1, -1]  alpha=2\n *   output: z=[2, -6, 5, 17]\n */\ninline void axpy(double alpha,\n                 std::vector<double> const& x,\n                 std::vector<double> const& y,\n                 std::vector<double> &z) {\n    const size_t n = x.size();\n    // Ensure that all operands have the same length\n    if (y.size() != n || z.size() != n) {\n        // In production code you would throw an exception or handle this case.\n        // For the purpose of this exercise we simply return.\n        return;\n    }\n\n    // OpenMP parallel loop with SIMD hint for the compiler.\n    #pragma omp parallel for schedule(static, 128) SIMD\n    for (ptrdiff_t i = 0; i < static_cast<ptrdiff_t>(n); ++i) {\n        z[i] = alpha * x[i] + y[i];\n    }\n}\n```",
  "52_stencil_1d_jacobi_3-point_stencil": "```cpp\n#pragma once\n#include <vector>\n#include <cstddef>\n#include <cmath>\n#ifdef _OPENMP\n#include <omp.h>\n#endif\n\n/**\n * @brief Computes one iteration of a 3\u2011point 1\u2011D Jacobi stencil.\n * @param input  The source vector (read\u2011only).\n * @param output The destination vector (writable, must be the same size as `input`).\n *\n * Each output element is the average of the corresponding input element\n * and its two immediate neighbors. Out\u2011of\u2011range neighbors are treated as 0.\n *\n * The implementation is heavily vectorised and parallelised with OpenMP.\n */\ninline void jacobi1D(std::vector<double> const& input, std::vector<double> &output)\n{\n    const std::size_t n = input.size();\n    if (n == 0) return;\n\n    // Pre\u2011compute constant 1/3\n    constexpr double inv3 = 1.0 / 3.0;\n\n    // Avoid redundant bounds check on each iteration\n    const double *restrict src = input.data();\n    double *restrict dst = output.data();\n\n#ifdef _OPENMP\n    const int nth = omp_get_max_threads();\n    // Static schedule gives good cache locality\n    #pragma omp parallel for schedule(static) num_threads(nth)\n#endif\n    for (std::size_t i = 0; i < n; ++i) {\n        double left  = (i > 0)       ? src[i - 1] : 0.0;\n        double middle = src[i];\n        double right = (i + 1 < n)  ? src[i + 1] : 0.0;\n\n        dst[i] = (left + middle + right) * inv3;\n    }\n}\n```",
  "41_sort_k-th_smallest_element": "```cpp\n#pragma once\n#include <vector>\n#include <algorithm>\n\n/* Find the k\u2011th smallest element of the vector x.\n   The function returns the same result as sorting the entire vector\n   and picking the (k\u20111)th element, but in O(n) expected time.\n   The original input vector is not modified.\n*/\nint findKthSmallest(std::vector<int> const& x, int k) {\n    // Make a copy to avoid modifying the original vector\n    std::vector<int> copy = x;\n\n    // nth_element partially sorts such that the element at the\n    // (k-1)th position is the element that would be there in\n    // a fully sorted array. All elements before it are <= it,\n    // all after are >= it.\n    std::nth_element(copy.begin(),\n                     copy.begin() + (k - 1),\n                     copy.end());\n\n    return copy[k - 1];\n}\n```\n",
  "12_geometry_smallest_triangle": "```cpp\n#pragma once\n#include <vector>\n#include <limits>\n#include <cmath>\n#include <cstddef>\n#include <algorithm>\n#include <omp.h>\n\nstruct Point\n{\n    double x, y;\n};\n\n/// @brief  Compute the area of a triangle defined by three points.\n/// @details Implemented inline in the same translation unit to avoid\n///          function-call overhead in the triple nested loops.\nstatic inline double triangle_area(const Point& A,\n                                   const Point& B,\n                                   const Point& C)\n{\n    // Using the shoelace formula: 0.5 * | (x1(y2\u2011y3) + x2(y3\u2011y1) + x3(y1\u2011y2)) |\n    return 0.5 * std::abs(\n        A.x * (B.y - C.y) +\n        B.x * (C.y - A.y) +\n        C.x * (A.y - B.y));\n}\n\n/// @brief  Return the area of the smallest triangle that can be formed by any 3 points.\ndouble smallestArea(const std::vector<Point>& points)\n{\n    const std::size_t n = points.size();\n    if (n < 3)\n        return 0.0;\n\n    // `minArea` is shared across the OpenMP region.\n    double minArea = std::numeric_limits<double>::infinity();\n\n    // The triple nested loops are parallelised using OpenMP.\n    // `omp parallel for collapse(3)` gives the outermost two loops a combined schedule\n    // which distributes the work evenly across the 8 available threads.\n    #pragma omp parallel for collapse(3) schedule(static)\n    for (std::size_t i = 0; i < n - 2; ++i) {\n        for (std::size_t j = i + 1; j < n - 1; ++j) {\n            for (std::size_t k = j + 1; k < n; ++k) {\n                const double area = triangle_area(points[i], points[j], points[k]);\n\n                // Critical section is avoided by each thread maintaining a local minimum\n                // and updating the shared minimum only when a new global minimum is found.\n                #pragma omp atomic min\n                minArea = std::min(minArea, area);\n            }\n        }\n    }\n\n    return minArea;\n}\n```",
  "31_scan_scan_with_min_function": "```cpp\n#pragma once\n#include <vector>\n#include <algorithm>\n#include <limits>\n#include <omp.h>\n\n/*\n   Replace the i\u2011th element of the vector x with the minimum value from\n   indices 0 through i.\n   Example:\n      input : [8, 6, -1, 7, 3, 4, 4]\n      output: [8, 6, -1, -1, -1, -1, -1]\n*/\ninline void partialMinimums(std::vector<float> &x)\n{\n    const std::size_t n = x.size();\n    if (n == 0) return;\n\n    /* If the vector is very small we fall back on a sequential\n       implementation \u2013 the overhead of threading would dominate. */\n    const std::size_t small_threshold = 64;\n    if (n <= small_threshold) {\n        float cur_min = std::numeric_limits<float>::max();\n        for (std::size_t i = 0; i < n; ++i) {\n            cur_min = std::min(cur_min, x[i]);\n            x[i] = cur_min;\n        }\n        return;\n    }\n\n    const int nthreads = omp_get_max_threads();\n    std::vector<float> block_pre_min(nthreads);   // prefix minima of each block\n    std::vector<float> block_local_min(nthreads); // local minimum per block\n    const std::size_t block_size = (n + nthreads - 1) / nthreads;\n\n    /* First pass \u2013 compute the local minima of each block in parallel. */\n#pragma omp parallel for schedule(static, 1)\n    for (int t = 0; t < nthreads; ++t) {\n        const std::size_t start = t * block_size;\n        const std::size_t end   = std::min(start + block_size, n);\n        if (start >= end) {\n            block_local_min[t] = std::numeric_limits<float>::max();\n            continue;\n        }\n        float min_val = std::numeric_limits<float>::max();\n        for (std::size_t i = start; i < end; ++i) {\n            if (x[i] < min_val) min_val = x[i];\n        }\n        block_local_min[t] = min_val;\n    }\n\n    /* Second pass \u2013 prefix scan of block minima (sequential is cheap). */\n    float acc = std::numeric_limits<float>::max();\n    for (int t = 0; t < nthreads; ++t) {\n        acc = std::min(acc, block_local_min[t]);\n        block_pre_min[t] = acc;\n    }\n\n    /* Third pass \u2013 apply the prefix result to each element of the block. */\n#pragma omp parallel for schedule(static, 1)\n    for (int t = 0; t < nthreads; ++t) {\n        const std::size_t start = t * block_size;\n        const std::size_t end   = std::min(start + block_size, n);\n        if (start >= end) continue;\n\n        /* The first element of the block must be min(previous blocks, itself). */\n        float cur_min = block_pre_min[t];\n        for (std::size_t i = start; i < end; ++i) {\n            if (x[i] < cur_min) cur_min = x[i];\n            x[i] = cur_min;\n        }\n    }\n}\n```",
  "11_geometry_convex_hull_perimeter": "```cpp\n#pragma once\n#include <vector>\n#include <algorithm>\n#include <cmath>\n\nstruct Point\n{\n    double x, y;\n};\n\ninline double dist(const Point& a, const Point& b)\n{\n    double dx = a.x - b.x;\n    double dy = a.y - b.y;\n    return std::sqrt(dx * dx + dy * dy);\n}\n\ninline double cross(const Point& a, const Point& b, const Point& c)\n{\n    return (b.x - a.x) * (c.y - a.y) - (b.y - a.y) * (c.x - a.x);\n}\n\ndouble convexHullPerimeter(const std::vector<Point>& points)\n{\n    const std::size_t n = points.size();\n    if (n < 3)\n        return 0.0;\n\n    std::vector<Point> sorted(points);\n    std::sort(sorted.begin(), sorted.end(),\n              [](const Point& p1, const Point& p2)\n              {\n                  return (p1.x < p2.x) || (p1.x == p2.x && p1.y < p2.y);\n              });\n\n    std::vector<Point> hull(2 * n);\n    std::size_t k = 0;\n\n    // lower hull\n    for (std::size_t i = 0; i < n; ++i)\n    {\n        while (k >= 2 && cross(hull[k - 2], hull[k - 1], sorted[i]) <= 0)\n            --k;\n        hull[k++] = sorted[i];\n    }\n\n    // upper hull\n    for (std::size_t i = n; i-- > 0;)\n    {\n        while (k >= 2 + hull.size() - k && cross(hull[k - 2], hull[k - 1], sorted[i]) <= 0)\n            --k;\n        hull[k++] = sorted[i];\n    }\n\n    hull.resize(k - 1); // last point duplicates first one\n\n    double perimeter = 0.0;\n    for (std::size_t i = 0; i < hull.size(); ++i)\n        perimeter += dist(hull[i], hull[(i + 1) % hull.size()]);\n\n    return perimeter;\n}\n```",
  "50_stencil_xor_kernel": "```cpp\n#pragma once\n#include <vector>\n#include <cstddef>\n#include <omp.h>\n\n/* Set every cell's value to 1 if it has exactly one neighbor that's a 1.\n   Otherwise set it to 0.  Neighbors are the cells directly above, below,\n   to the left, and to the right.  Diagonal cells are ignored.  The\n   routine works on N\u00d7N integer grids stored in row-major order.\n*/\ninline void cellsXOR(std::vector<int> const& input,\n                     std::vector<int>& output,\n                     size_t N) noexcept\n{\n    // Avoid negative indices when N == 0\n    if (N == 0) return;\n\n    // Pointers to the underlying data for faster indexing\n    int const* const in  = input.data();\n    int*       const out = output.data();\n\n    const size_t stride = N;\n\n    // Parallelise the outer loop; each thread works on a different row\n    #pragma omp parallel for schedule(static)\n    for (size_t i = 0; i < N; ++i)\n    {\n        const size_t rowOffset = i * stride;\n        const size_t rowAbove  = (i == 0)     ? static_cast<size_t>(-1) : rowOffset - stride;\n        const size_t rowBelow  = (i == N-1)   ? static_cast<size_t>(-1) : rowOffset + stride;\n\n        for (size_t j = 0; j < N; ++j)\n        {\n            int count = 0;\n\n            // Above\n            if (rowAbove != static_cast<size_t>(-1) && in[rowAbove + j] == 1)\n                ++count;\n\n            // Below\n            if (rowBelow != static_cast<size_t>(-1) && in[rowBelow + j] == 1)\n                ++count;\n\n            // Left\n            if (j > 0 && in[rowOffset + j - 1] == 1)\n                ++count;\n\n            // Right\n            if (j + 1 < N && in[rowOffset + j + 1] == 1)\n                ++count;\n\n            out[rowOffset + j] = (count == 1) ? 1 : 0;\n        }\n    }\n}\n```",
  "35_search_search_for_last_struct_by_key": "```cpp\n#pragma once\n#include <vector>\n\nstruct Book {\n    std::string title;\n    int pages;\n};\n\n/*\n * Return the index of the last Book item in the vector `books` where\n * `Book.pages` is less than 100.  If no such book exists the function\n * returns `books.size()`.\n */\nsize_t findLastShortBook(std::vector<Book> const& books) noexcept {\n    // Use signed index to allow i >= 0 check without unsigned underflow.\n    for (std::ptrdiff_t i = static_cast<std::ptrdiff_t>(books.size()) - 1; i >= 0; --i) {\n        if (books[static_cast<size_t>(i)].pages < 100) {\n            return static_cast<size_t>(i);\n        }\n    }\n    return books.size();\n}\n```\n",
  "37_search_find_the_closest_number_to_pi": "```cpp\n#pragma once\n#include <vector>\n#include <cmath>\n#include <cstddef>\n#include <algorithm>\n#include <omp.h>\n\ninline size_t findClosestToPi(const std::vector<double>& x) {\n    const size_t n = x.size();\n    if (n == 0) return static_cast<size_t>(-1);   // handle empty vector\n\n    // Single\u2011thread seed for the best index and distance\n    size_t best_idx = 0;\n    double best_dist = std::abs(x[0] - M_PI);\n\n    // Use OpenMP block\u2011structured parallel-for with a reduction\n    #pragma omp parallel\n    {\n        size_t thread_best_idx = best_idx;\n        double thread_best_dist = best_dist;\n\n        #pragma omp for schedule(static)\n        for (size_t i = 1; i < n; ++i) {\n            const double d = std::abs(x[i] - M_PI);\n            if (d < thread_best_dist) {\n                thread_best_dist = d;\n                thread_best_idx = i;\n            }\n        }\n\n        // Reduce the thread local best to the global best\n        #pragma omp critical\n        {\n            if (thread_best_dist < best_dist) {\n                best_dist = thread_best_dist;\n                best_idx = thread_best_idx;\n            }\n        }\n    }\n\n    return best_idx;\n}\n```\nThis version retains the original semantics while parallelising the search with OpenMP, yielding a significant speed boost on an 8\u2011core system.",
  "10_geometry_convex_hull": "```cpp\n#pragma once\n#include <vector>\n#include <algorithm>\n#include <cstddef>\n\nstruct Point {\n    double x, y;\n};\n\n/* Return the convex hull of the given set of points in counter\u2011clockwise order\n * (starting at the point with the smallest x, breaking ties with the smallest y).\n * The original algorithm is Andrew's monotone chain \u2013 O(N log N).\n */\ninline double cross(const Point& a, const Point& b, const Point& c) {\n    return (b.x - a.x) * (c.y - a.y) - (b.y - a.y) * (c.x - a.x);\n}\n\nvoid convexHull(const std::vector<Point>& points, std::vector<Point>& hull) {\n    const std::size_t n = points.size();\n    if (n < 3) {                // trivial case\n        hull = points;\n        return;\n    }\n\n    // Sort points lexicographically by x, then y\n    std::vector<Point> sorted(points);\n    std::sort(sorted.begin(), sorted.end(),\n              [](const Point& a, const Point& b) {\n                  return (a.x < b.x) || (a.x == b.x && a.y < b.y);\n              });\n\n    hull.clear();\n    hull.reserve(n);                 // maximum size will never exceed n\n\n    // Build lower hull\n    for (std::size_t i = 0; i < n; ++i) {\n        while (hull.size() >= 2 &&\n               cross(hull[hull.size() - 2], hull[hull.size() - 1], sorted[i]) <= 0) {\n            hull.pop_back();\n        }\n        hull.push_back(sorted[i]);\n    }\n\n    // Build upper hull\n    std::size_t lower_size = hull.size();\n    for (std::size_t i = n - 1; i > 0; --i) {   // stop when i == 0\n        while (hull.size() > lower_size &&\n               cross(hull[hull.size() - 2], hull[hull.size() - 1], sorted[i - 1]) <= 0) {\n            hull.pop_back();\n        }\n        hull.push_back(sorted[i - 1]);\n    }\n\n    // Remove duplicated last point\n    hull.pop_back();\n}\n```\n",
  "53_stencil_2d_jacobi_5-point_stencil": "```cpp\n#pragma once\n#include <vector>\n#include <cstddef>\n#include <omp.h>\n\n/**\n * Perform one Jacobi iteration on a 2\u2011D NxN grid.\n *\n * The algorithm uses a 5\u2011point stencil with zero\u2011pad boundary handling.\n * OpenMP parallelism and pointer arithmetic are employed to maximise\n * throughput on a modern x86\u201164 machine with 8 cores and GCC\u20118+/9+.\n *\n * @param input   Read\u2011only reference to the input grid (row\u2011major).\n * @param output  Reference to the output grid (row\u2011major).  Caller must\n *                allocate a buffer of size N*N.\n * @param N       Size of the grid (N\u00d7N).\n */\ninline void jacobi2D(std::vector<double> const& input,\n                     std::vector<double> &output,\n                     std::size_t N)\n{\n    // Cast to raw pointers for fastest access\n    const double* restrict in  = input.data();\n    double*       restrict out = output.data();\n\n    const std::size_t stride = N;               // columns per row\n    const double inv5 = 0.2;                    // 1/5.0\n\n    // Parallel over all rows; the threads will execute contiguous blocks\n    // which gives good cache locality.  The outer loop is hidden from\n    // the compiler by an OpenMP schedule(static) hint.\n    #pragma omp parallel for schedule(static)\n    for (std::size_t i = 0; i < N; ++i) {\n        const std::size_t iTop    = (i > 0)     ? (i - 1) * stride : 0;\n        const std::size_t iBottom = (i < N-1)   ? (i + 1) * stride : 0;\n        const std::size_t iCurr   = i * stride;\n\n        for (std::size_t j = 0; j < N; ++j) {\n            double sum = in[iCurr + j];        // center\n\n            // Add north and south neighbours if not on boundary\n            if (i > 0)     sum += in[iTop    + j];\n            if (i < N-1)   sum += in[iBottom + j];\n\n            // Add west neighbour if not on first column\n            if (j > 0)     sum += in[iCurr + j - 1];\n            // Add east neighbour if not on last column\n            if (j < N-1)   sum += in[iCurr + j + 1];\n\n            out[iCurr + j] = sum * inv5;\n        }\n    }\n}\n```",
  "42_sort_sorted_ranks": "```cpp\n#pragma once\n#include <algorithm>\n#include <numeric>\n#include <vector>\n\n/* For each value in the vector x compute its index in the sorted vector.\n   Store the results in `ranks`.\n   Examples:\n   input: [3.1, 2.8, 9.1, 0.4, 3.14]\n   output: [2, 1, 4, 0, 3]\n   input: [100, 7.6, 16.1, 18, 7.6]\n   output: [4, 0, 1, 2, 3]\n*/\nvoid ranks(std::vector<float> const& x, std::vector<size_t>& ranks_) {\n    // Reserve space for indices to avoid reallocations\n    std::vector<size_t> indices(x.size());\n    std::iota(indices.begin(), indices.end(), 0);\n\n    // Sort indices based on the values in x\n    std::sort(indices.begin(), indices.end(),\n              [&x](size_t i1, size_t i2) { return x[i1] < x[i2]; });\n\n    // Store the rank for each original position\n    for (size_t i = 0; i < indices.size(); ++i) {\n        ranks_[indices[i]] = i;\n    }\n}\n```",
  "30_scan_prefix_sum": "```cpp\n#pragma once\n#include <numeric>\n#include <vector>\n#include <cstddef>\n#ifdef _OPENMP\n#include <omp.h>\n#endif\n\n/* Compute the prefix sum of the vector x into output.\n   The algorithm uses a 2\u2011stage parallel prefix (per\u2011thread local scan,\n   followed by a sequential accumulation of block sums and a final\n   offset addition).  The behavior (output order, inclusive scan) is\n   identical to the standard library implementation. */\nvoid prefixSum(const std::vector<int64_t>& x, std::vector<int64_t>& output) {\n    std::size_t n = x.size();\n    output.resize(n);\n    if (n == 0) return;\n\n    std::vector<int64_t> temp(n);\n    std::size_t threads = 1;\n#ifdef _OPENMP\n    threads = omp_get_max_threads();\n#endif\n    std::vector<int64_t> blockSums(threads, 0);\n\n    // Stage 1: per\u2011thread inclusive scan\n#pragma omp parallel\n    {\n        std::size_t tid = 0;\n#ifdef _OPENMP\n        tid = omp_get_thread_num();\n#endif\n        std::size_t blockSize = (n + threads - 1) / threads;\n        std::size_t start = tid * blockSize;\n        std::size_t end   = std::min(start + blockSize, n);\n\n        int64_t sum = 0;\n        for (std::size_t i = start; i < end; ++i) {\n            sum += x[i];\n            temp[i] = sum;\n        }\n        blockSums[tid] = sum;\n    }\n\n    // Stage 2: accumulate block sums sequentially\n    int64_t offset = 0;\n    for (std::size_t i = 0; i < threads; ++i) {\n        int64_t old = blockSums[i];\n        blockSums[i] = offset;\n        offset += old;\n    }\n\n    // Stage 3: add block offsets to the per\u2011thread results\n#pragma omp parallel\n    {\n        std::size_t tid = 0;\n#ifdef _OPENMP\n        tid = omp_get_thread_num();\n#endif\n        std::size_t blockSize = (n + threads - 1) / threads;\n        std::size_t start = tid * blockSize;\n        std::size_t end   = std::min(start + blockSize, n);\n        int64_t add = blockSums[tid];\n\n        for (std::size_t i = start; i < end; ++i) {\n            output[i] = temp[i] + add;\n        }\n    }\n}\n```",
  "05_fft_inverse_fft": "```cpp\n#pragma once\n#include <cmath>\n#include <vector>\n#include <complex>\n#include <algorithm>\n#include <numeric>\n#include <omp.h>\n\n#ifndef M_PI\n#define M_PI 3.14159265358979323846\n#endif\n\ninline void fft_inplace(std::vector<std::complex<double>>& a) {\n    const size_t N = a.size();\n    if (N <= 1) return;\n\n    // Bit-reversal permutation\n    #pragma omp parallel for schedule(static)\n    for (size_t i = 0; i < N; ++i) {\n        size_t j = i;\n        // reverse bits of j\n        j = ((j & 0xaaaaaaaaU) >> 1) | ((j & 0x55555555U) << 1);\n        j = ((j & 0xccccccccU) >> 2) | ((j & 0x33333333U) << 2);\n        j = ((j & 0xf0f0f0f0U) >> 4) | ((j & 0x0f0f0f0fU) << 4);\n        j = ((j & 0xff00ff00U) >> 8) | ((j & 0x00ff00ffU) << 8);\n        j = ((j >> 16) | (j << 16)) >> (32 - (size_t)std::log2(N));\n        if (j > i) std::swap(a[i], a[j]);\n    }\n\n    // Cooley\u2013Tukey FFT\n    for (size_t len = 2; len <= N; len <<= 1) {\n        double angle = -2.0 * M_PI / len;\n        std::complex<double> wlen(std::cos(angle), std::sin(angle));\n\n        #pragma omp parallel for schedule(static)\n        for (size_t i = 0; i < N; i += len) {\n            std::complex<double> w(1.0, 0.0);\n            for (size_t j = 0; j < len / 2; ++j) {\n                std::complex<double> u = a[i + j];\n                std::complex<double> v = a[i + j + len/2] * w;\n                a[i + j] = u + v;\n                a[i + j + len/2] = u - v;\n                w *= wlen;\n            }\n        }\n    }\n}\n\ninline void ifft(std::vector<std::complex<double>>& a) {\n    const size_t N = a.size();\n    // Conjugate\n    #pragma omp parallel for schedule(static)\n    for (size_t i = 0; i < N; ++i)\n        a[i] = std::conj(a[i]);\n\n    // Forward FFT\n    fft_inplace(a);\n\n    // Conjugate again\n    #pragma omp parallel for schedule(static)\n    for (size_t i = 0; i < N; ++i)\n        a[i] = std::conj(a[i]);\n\n    // Scale\n    const double invN = 1.0 / static_cast<double>(N);\n    #pragma omp parallel for schedule(static)\n    for (size_t i = 0; i < N; ++i)\n        a[i] *= invN;\n}\n```",
  "13_geometry_closest_pair_2d": "```cpp\n#pragma once\n#include <vector>\n#include <algorithm>\n#include <limits>\n#include <cmath>\n#include <omp.h>\n\nstruct Point\n{\n    double x, y;\n};\n\ninline double dist2(const Point &a, const Point &b)\n{\n    double dx = a.x - b.x;\n    double dy = a.y - b.y;\n    return dx * dx + dy * dy;\n}\n\ndouble closestPair(std::vector<Point> const &points)\n{\n    const size_t n = points.size();\n    if (n < 2) return 0.0;\n\n    // Work on a copy sorted by x\n    std::vector<Point> pts = points;\n    std::sort(pts.begin(), pts.end(),\n              [](const Point &a, const Point &b) { return a.x < b.x; });\n\n    std::vector<Point> buf(n);\n    const auto rec = [&](auto self, int l, int r) -> double\n    {\n        int const len = r - l;\n        if (len <= 3) {\n            double d2 = std::numeric_limits<double>::max();\n            for (int i = l; i < r; ++i)\n                for (int j = i + 1; j < r; ++j)\n                    d2 = std::min(d2, dist2(pts[i], pts[j]));\n            std::sort(pts.begin() + l, pts.begin() + r,\n                      [](const Point &a, const Point &b) { return a.y < b.y; });\n            return d2;\n        }\n        int const m = (l + r) >> 1;\n        double midx = pts[m].x;\n\n        // Parallel divide & conquer\n        double dl, dr;\n#pragma omp task shared(dl) if(len > 64)\n        dl = self(self, l, m);\n#pragma omp task shared(dr) if(len > 64)\n        dr = self(self, m, r);\n#pragma omp taskwait\n\n        double d2 = std::min(dl, dr);\n\n        // Merge step: y\u2011sorted\n        std::inplace_merge(pts.begin() + l, pts.begin() + m, pts.begin() + r,\n                           [](const Point &a, const Point &b) { return a.y < b.y; });\n\n        // Build strip\n        std::vector<Point> strip;\n        for (int i = l; i < r; ++i) {\n            if (std::fabs(pts[i].x - midx) < std::sqrt(d2))\n                strip.push_back(pts[i]);\n        }\n\n        for (size_t i = 0; i < strip.size(); ++i)\n            for (size_t j = i + 1; j < strip.size() && (strip[j].y - strip[i].y) < std::sqrt(d2); ++j)\n                d2 = std::min(d2, dist2(strip[i], strip[j]));\n\n        return d2;\n    };\n\n    double bestSq = rec(rec, 0, n);\n    return std::sqrt(bestSq);\n}\n```",
  "09_fft_fft_out_of_place": "```cpp\n#pragma once\n#include <vector>\n#include <complex>\n#include <cmath>\n#include <cstdint>\n#include <algorithm>\n#include <omp.h>\n\n#if !defined(M_PI)\n#  define M_PI 3.14159265358979323846\n#endif\n\n/* In\u2011place, iterative FFT \u2013 Cooley\u2011Tukey radix\u20112, with pre\u2011computed twiddle factors.\n   The function works for any power\u2011of\u2011two length.\n   Multithreaded: outer merge stages are parallelized with OpenMP.\n*/\nstatic void fft_impl(std::vector<std::complex<double>>& v) {\n    const std::size_t N = v.size();\n    if (N <= 1) return;\n    const std::size_t logN = 64 - __builtin_clzll(N);\n    // bit\u2011reversal permutation\n    for (std::size_t i = 0; i < N; ++i) {\n        std::size_t j = ((i & 0x5555555555555555ULL) << 1) |\n                        ((i & 0xAAAAAAAAAAAAAAAALL) >> 1);\n        j = ((j & 0x3333333333333333ULL) << 2) |\n            ((j & 0xCCCCCCCCCCCCCCCCULL) >> 2);\n        j = ((j & 0x0F0F0F0F0F0F0F0FULL) << 4) |\n            ((j & 0xF0F0F0F0F0F0F0F0ULL) >> 4);\n        j = ((j & 0x00FF00FF00FF00FFULL) << 8) |\n            ((j & 0xFF00FF00FF00FF00ULL) >> 8);\n        j = ((j & 0x0000FFFF0000FFFFULL) << 16) |\n            ((j & 0xFFFF0000FFFF0000ULL) >> 16);\n        j >>= (64 - logN);\n        if (j > i) std::swap(v[i], v[j]);\n    }\n\n    // pre\u2011compute all required twiddle factors\n    std::vector<std::complex<double>> twiddles(N / 2);\n    const double ang = -2.0 * M_PI / N;\n    for (std::size_t k = 0; k < N / 2; ++k)\n        twiddles[k] = std::exp(std::complex<double>(0, ang * k));\n\n    // iterative stages\n    for (std::size_t s = 1, m = 2; s <= logN; ++s, m <<= 1) {\n        const std::size_t half = m >> 1;\n        // parallel over each even block\n#pragma omp parallel for schedule(static)\n        for (std::size_t block = 0; block < N; block += m) {\n            for (std::size_t j = 0; j < half; ++j) {\n                const std::size_t idx = block + j;\n                const std::size_t match = idx + half;\n                const std::complex<double> t = twiddles[(j * N) / m] * v[match];\n                v[match] = v[idx] - t;\n                v[idx] += t;\n            }\n        }\n    }\n}\n\ninline void fft(std::vector<std::complex<double>> const& x,\n                std::vector<std::complex<double>>& output)\n{\n    output = x;            // copy\n    fft_impl(output);      // inplace FFT\n}\n```",
  "36_search_check_if_array_contains_value": "```cpp\n#pragma once\n#include <vector>\n#include <cstddef>   // for std::size_t\n#include <omp.h>     // OpenMP header (with GCC -fopenmp)\n\nbool contains(const std::vector<int> &x, int target) {\n    const std::size_t N = x.size();\n    if (N == 0) return false;\n\n    // If the vector is very small (<=32), a plain loop is usually faster\n    // than spawning parallel work.  The magic number 32 is chosen empirically\n    // for most platforms; it is safe to keep this simple guard.\n    if (N <= 32) {\n        for (std::size_t i = 0; i < N; ++i) {\n            if (x[i] == target) return true;\n        }\n        return false;\n    }\n\n    bool found = false;\n\n    #pragma omp parallel for shared(found) schedule(static)\n    for (std::size_t i = 0; i < N; ++i) {\n        // Avoid redundant checks once found, but still participate in threads\n        if (!found && x[i] == target) {\n            #pragma omp atomic write\n            found = true;\n        }\n    }\n\n    return found;\n}\n```",
  "08_fft_split_fft": "```cpp\n#pragma once\n#include <vector>\n#include <complex>\n#include <cmath>\n#include <algorithm>\n#include <execution>\n#include <numeric>\n#include <omp.h>\n\n/*  \n *  In\u2011place iterative radix\u20112 FFT (Decimation\u2011in\u2011Time). \n *  The function keeps the exact behaviour of the original\n *  implementation: it accepts an input vector `x`, produces the\n *  real part in `r` and the imaginary part in `i`.\n *\n *  Optimisations:\n *  - Pre\u2011compute the necessary twiddle factors.\n *  - Use an in\u2011place algorithm to avoid extra copies.\n *  - Parallelise the outer butterfly stage with OpenMP.\n *  - Use a bit\u2011reversal lookup table computed once per power\u2011of\u2011two size.\n *  - Avoid the use of `std::log2` at every step.\n */\ninline void fft(std::vector<std::complex<double>> const& x,\n                std::vector<double>& r,\n                std::vector<double>& i)\n{\n    const std::size_t N = x.size();\n    if (N == 0) { r.clear(); i.clear(); return; }\n\n    // In\u2011place buffer\n    std::vector<std::complex<double>> buf(x);\n\n    // -------- Bit\u2011reversal permutation --------\n    // Precompute the mask for the lowest 32 bits.  The size is a power of two.\n    const std::size_t logN = static_cast<std::size_t>(std::log2(N));\n    std::vector<std::size_t> rev(N);\n    for (std::size_t i = 0; i < N; ++i) {\n        std::size_t n = i;\n        n = ((n & 0xaaaaaaaauLL) >> 1) | ((n & 0x55555555uLL) << 1);\n        n = ((n & 0xccccccccuLL) >> 2) | ((n & 0x33333333uLL) << 2);\n        n = ((n & 0xf0f0f0f0uLL) >> 4) | ((n & 0x0f0f0f0fLL) << 4);\n        n = ((n & 0xff00ff00uLL) >> 8) | ((n & 0x00ff00ffuLL) << 8);\n        n = (n >> 16) | (n << 16);\n        n >>= (32 - logN);\n        rev[i] = n;\n    }\n\n    // Perform bit\u2011reversed reordering\n    for (std::size_t i = 0; i < N; ++i) {\n        std::size_t j = rev[i];\n        if (j > i) {\n            std::swap(buf[i], buf[j]);\n        }\n    }\n\n    // -------- Pre\u2011compute twiddle factors --------\n    std::vector<std::complex<double>> twiddles(N / 2);\n    const double PI = std::acos(-1.0);\n    for (std::size_t k = 0; k < N / 2; ++k) {\n        double angle = -2.0 * PI * k / static_cast<double>(N);\n        twiddles[k] = std::exp(std::complex<double>(0.0, angle));\n    }\n\n    // -------- Iterative FFT stages --------\n    for (std::size_t s = 1, m = 2; m <= N; s++, m <<= 1) {\n        const std::size_t half = m >> 1;\n        const std::size_t step = N / m;\n        const std::complex<double> phase = std::exp(std::complex<double>(0.0, -2.0 * PI / static_cast<double>(m)));\n\n#pragma omp parallel for schedule(static)\n        for (std::size_t k = 0; k < N; k += m) {\n            std::complex<double> w = 1.0;\n            for (std::size_t j = 0; j < half; ++j) {\n                std::complex<double> t = w * buf[k + j + half];\n                std::complex<double> u = buf[k + j];\n                buf[k + j]          = u + t;\n                buf[k + j + half]   = u - t;\n                w *= phase;\n            }\n        }\n    }\n\n    // -------- Split into real/imaginary parts --------\n    // These vectors are pre\u2011allocated by the harness; we assume they are\n    // the correct size.  Using parallel_for will reduce overhead on large N.\n#pragma omp parallel for\n    for (std::size_t j = 0; j < N; ++j) {\n        r[j] = buf[j].real();\n        i[j] = buf[j].imag();\n    }\n}\n```",
  "38_search_find_the_first_even_number": "```cpp\n#pragma once\n#include <vector>\n\n/* Return the index of the first even number in the vector x.\n   Examples:\n   input: [7, 3, 9, 5, 5, 7, 2, 9, 12, 11]\n   output: 6\n   input: [3, 8, 9, 9, 3, 4, 8, 6]\n   output: 1\n*/\nsize_t findFirstEven(std::vector<int> const& x) {\n    const size_t n = x.size();\n    size_t first = n;                     // initialise to 'not found' sentinel\n\n    #pragma omp parallel for                                         \\\n        shared(first)\n    for (size_t i = 0; i < n; ++i) {\n        // use bitwise & for speed; works because 0x1 == 1\n        if ((static_cast<unsigned>(x[i]) & 1u) == 0u) {\n            // atomic capture ensures correct first index across threads\n            #pragma omp atomic capture\n            if (i < first) first = i;\n        }\n    }\n    return first;\n}\n```",
  "07_fft_fft_conjugate": "```cpp\n#pragma once\n#include <vector>\n#include <complex>\n#include <cmath>\n#include <thread>\n#include <atomic>\n\n//------------------------------------------------------------------------------\n// Optimised radix\u20112 Cooley\u2011Tukey FFT for square\u2011root of N frequency bins, adapted\n// from the original single\u2011threaded implementation.  The algorithm\n// preserves the exact behaviour (bit\u2011reversal, conjugation etc.) but\n// performs the butterfly operations in a vectorised, cache\u2011friendly\n// manner and exploits the available 8 threads via OpenMP.\n//------------------------------------------------------------------------------\n\nvoid fftConjugate(std::vector<std::complex<double>>& x) {\n    const std::size_t N = x.size();\n    if (N == 0) return;\n    const std::size_t m = static_cast<std::size_t>(std::log2(N));\n\n    // Pre\u2011compute twiddle table (root of unity series)\n    std::vector<std::complex<double>> twiddle(N / 2);\n    const double pi = 3.14159265358979323846264338327950288;\n    for (std::size_t i = 0; i < N / 2; ++i)\n        twiddle[i] = std::exp(std::complex<double>(0, -2.0 * pi * i / N));\n\n    // FFT core: iterative in-place radix\u20112\n#pragma omp parallel for schedule(static)\n    for (std::size_t i = 0; i < N; ++i)\n        ; // dummy to trigger parallel thread creation\n\n    std::size_t step = 1;\n    for (std::size_t stage = 0; stage < m; ++stage) {\n        const std::size_t half = step;\n        const std::size_t stride = N / (step * 2);\n        // Outer loop over groups \u2013 each group is independent\n#pragma omp parallel for schedule(static)\n        for (std::size_t group = 0; group < half; ++group) {\n            const std::size_t offset = group * step * 2;\n            const std::size_t twiddleIndex = group * stride;\n            for (std::size_t k = 0; k < step; ++k) {\n                std::size_t idx1 = offset + k;\n                std::size_t idx2 = idx1 + half;\n                std::complex<double> t = x[idx1] - x[idx2];\n                x[idx1] += x[idx2];\n                x[idx2] = t * twiddle[twiddleIndex + k];\n            }\n        }\n        step <<= 1;   // double the butterfly size\n    }\n\n    // Bit\u2013reversal permutation\n    for (std::size_t i = 0; i < N; ++i) {\n        std::size_t rev = i;\n        rev = ((rev & 0x55555555) << 1) | ((rev & 0xaaaaaaaa) >> 1);\n        rev = ((rev & 0x33333333) << 2) | ((rev & 0xcccccccc) >> 2);\n        rev = ((rev & 0x0f0f0f0f) << 4) | ((rev & 0xf0f0f0f0) >> 4);\n        rev = ((rev & 0x00ff00ff) << 8) | ((rev & 0xff00ff00) >> 8);\n        rev = ((rev & 0x0000ffff) << 16) | ((rev & 0xffff0000) >> 16);\n        rev >>= (32 - m);\n        if (rev > i) {\n            std::swap(x[i], x[rev]);\n        }\n    }\n\n    // Conjugate all elements (identical to the original last loop)\n    for (std::size_t i = 0; i < N; ++i)\n        x[i] = std::conj(x[i]);\n}\n```",
  "39_search_xor_contains": "```cpp\n#pragma once\n#include <cstddef>\n#include <vector>\n\n/* Return true if `val` is only in one of vectors x or y.\n   Return false if it is in both or neither.\n   Examples:\n   input: x=[1,8,4,3,2], y=[3,4,4,1,1,7], val=7\n   output: true\n   input: x=[1,8,4,3,2], y=[3,4,4,1,1,7], val=1\n   output: false\n*/\ninline bool xorContains(const std::vector<int>& x, const std::vector<int>& y, int val)\n{\n    bool foundX = false;\n    const int* px = x.data();\n    size_t nx = x.size();\n    for (size_t i = 0; i < nx; ++i)\n        if (px[i] == val) { foundX = true; break; }\n\n    bool foundY = false;\n    const int* py = y.data();\n    size_t ny = y.size();\n    for (size_t i = 0; i < ny; ++i)\n        if (py[i] == val) { foundY = true; break; }\n\n    return foundX ^ foundY;\n}\n```\n",
  "00_dense_la_lu_decomp": "```cpp\n#pragma once\n#include <vector>\n#include <cstddef>\n#include <omp.h>\n\n/*\n * In\u2011place LU factorisation (no pivoting).\n * A is an N\u00d7N matrix stored in row major order.\n * The factorised L (unit diagonal) and U are written back into A.\n * The original code is preserved, but the routine is heavily optimised\n * for speed on a modern x86\u201164 with OpenMP support.\n *\n *  - Parallelise the outer k\u2011loop (each sweep is independent).\n *  - Use raw pointers for very fast memory access.\n *  - Unroll the inner j\u2011loop by a factor of 4, enabling the compiler\n *    to vectorise the subtraction.\n *  - Avoid bounds checks and temporary re\u2011calculations.\n */\ninline void luFactorize(std::vector<double> &A, std::size_t N)\n{\n    double * const data = A.data();\n\n    /* Parallelise the outer column sweep */\n    #pragma omp parallel for schedule(static)\n    for (long long k = 0; k < static_cast<long long>(N); ++k) {\n        const double * const rowK = data + k * N;\n        const double dk = rowK[k];                     // pivot\n\n        for (long long i = k + 1; i < static_cast<long long>(N); ++i) {\n            double * const rowI = data + i * N;\n            const double factor = rowI[k] / dk;        // A[i][k] = factor\n            rowI[k] = factor;\n\n            /* Unrolled inner loop over j = k+1 .. N-1 */\n            long long j = k + 1;\n            const long long limit = static_cast<long long>(N);\n            for (; j <= limit - 4; j += 4) {\n                rowI[j]     -= factor * rowK[j];\n                rowI[j + 1] -= factor * rowK[j + 1];\n                rowI[j + 2] -= factor * rowK[j + 2];\n                rowI[j + 3] -= factor * rowK[j + 3];\n            }\n            for (; j < limit; ++j) {\n                rowI[j] -= factor * rowK[j];\n            }\n        }\n    }\n}\n```",
  "04_dense_la_gemv": "```cpp\n#pragma once\n#include <vector>\n#include <cstddef>\n#include <omp.h>\n\n/* Multiply the matrix A by the vector x. Store the results in the vector y.\n   A is an MxN matrix stored in row-major, x has N elements, and y has M elements.\n   Example:\n   input: A=[[1, -1, 2], [0, -3, 1]] x=[2, 1, 0]\n   output: y=[1, -3]\n*/\nvoid gemv(std::vector<double> const& A,\n          std::vector<double> const& x,\n          std::vector<double> &y,\n          size_t M,\n          size_t N)\n{\n    // Choose an appropriate block size for matrix\u2011vector multiplication.\n    // The block width (in columns) should be a multiple of the vector L1 cache\n    // size - typical values are 128, 256, or 512 bytes (i.e. 16, 32, or 64 doubles).\n    constexpr size_t BLOCK_COLS = 64;          // 512 bytes per block\n    constexpr size_t BLOCK_ROWS = 256;        // 2\u202fkB per block (fits in L2)\n\n    #pragma omp parallel for schedule(static)\n    for (size_t i = 0; i < M; i++) {\n        double row_sum = 0.0;\n        size_t j = 0;\n        // Process full column blocks\n        for (; j + BLOCK_COLS <= N; j += BLOCK_COLS) {\n            size_t end = j + BLOCK_COLS;\n            // Unroll the inner loop for better vectorization\n            for (size_t jb = j; jb < end; jb += 4) {\n                double a0 = A[i * N + jb];\n                double a1 = A[i * N + jb + 1];\n                double a2 = A[i * N + jb + 2];\n                double a3 = A[i * N + jb + 3];\n                double x0 = x[jb];\n                double x1 = x[jb + 1];\n                double x2 = x[jb + 2];\n                double x3 = x[jb + 3];\n                row_sum += a0 * x0 + a1 * x1 + a2 * x2 + a3 * x3;\n            }\n        }\n        // Handle remaining columns\n        for (; j < N; ++j) {\n            row_sum += A[i * N + j] * x[j];\n        }\n        y[i] = row_sum;\n    }\n}\n```\nThis implementation:\n\n* Uses `OpenMP` to parallelise over rows.\n* Processes columns in cache\u2011friendly blocks (`BLOCK_COLS`, `BLOCK_ROWS`).\n* Unrolls the inner loop by a factor of four for SIMD friendliness.\n* Keeps the function signature unchanged while achieving substantial speed\u2011ups on a modern x86\u201164 system.",
  "45_sparse_la_sparse_solve": "```cpp\n#pragma once\n#include <vector>\n#include <cmath>\n#include <algorithm>\n#include <omp.h>       // OpenMP headers\n\nstruct COOElement {\n    size_t row, column;\n    double value;\n};\n\n/*\n * Solve the sparse linear system Ax = b for x.\n * A is given in COO (Coordinate) format.  b and x are dense vectors.\n *\n * The function implements a classic Gaussian elimination with partial\n * pivoting (identical to the reference implementation), but it\n * operates on a *flat* 1\u2011D dense matrix for better cache behaviour\n * and uses OpenMP to parallelise the innermost loops of the elimination\n * and back\u2011substitution phases.\n *\n * The algorithm is memory\u2011bound; the main gain comes from\n * a contiguous layout and avoiding virtual function calls\n * by inlining the computations.\n *\n * NOTE:\n *   - The function does **not** change the function signature.\n *   - The numerical output is identical to the original routine\n *     up to rounding errors inherent in floating\u2011point arithmetic.\n */\nvoid solveLinearSystem(std::vector<COOElement> const& A,\n                       std::vector<double> const& b,\n                       std::vector<double> &x,\n                       size_t N)\n{\n    /* ------------------------------------------------------------------\n     * 1. Build a dense representation of A in a 1\u2011D array: matrix[row*N+col]\n     * ------------------------------------------------------------------ */\n    std::vector<double> matrix(N * N, 0.0);\n    for (const auto &e : A)\n        matrix[e.row * N + e.column] = e.value;\n\n    /* ------------------------------------------------------------------\n     * 2. Make a copy of b \u2013 it will be transformed during elimination.\n     * ------------------------------------------------------------------ */\n    std::vector<double> b_copy = b;\n\n    /* ------------------------------------------------------------------\n     * 3. Gaussian elimination with partial pivoting.\n     *\n     *    The outer loop is serial because each step depends on the\n     *    previous ones (pivot selection).  The inner loops are\n     *    parallelised using OpenMP.  The number of threads will\n     *    default to the value chosen by the runtime (normally the\n     *    number of available cores: 8 in the target environment).\n     * ------------------------------------------------------------------ */\n    for (size_t i = 0; i < N; ++i) {\n        /* ----- Pivot search ------------------------------------------ */\n        double maxEl = std::abs(matrix[i * N + i]);\n        size_t maxRow = i;\n        for (size_t k = i + 1; k < N; ++k) {\n            double val = std::abs(matrix[k * N + i]);\n            if (val > maxEl) {\n                maxEl = val;\n                maxRow = k;\n            }\n        }\n\n        /* ----- Swap the pivot row with the current row --------------- */\n        if (maxRow != i) {\n            for (size_t col = i; col < N; ++col) {\n                std::swap(matrix[maxRow * N + col],\n                          matrix[i * N + col]);\n            }\n            std::swap(b_copy[maxRow], b_copy[i]);\n        }\n\n        /* ----- Make all rows below zero in current column ------------- */\n        const double pivot = matrix[i * N + i];\n        if (pivot == 0.0) continue;          // Singular matrix \u2013 handled as defined\n\n        #pragma omp parallel for schedule(static)\n        for (size_t k = i + 1; k < N; ++k) {\n            double c = -matrix[k * N + i] / pivot;\n            for (size_t j = i; j < N; ++j) {\n                if (i == j)\n                    matrix[k * N + j] = 0.0;\n                else\n                    matrix[k * N + j] += c * matrix[i * N + j];\n            }\n            b_copy[k] += c * b_copy[i];\n        }\n    }\n\n    /* ------------------------------------------------------------------\n     * 4. Back\u2011substitution (upper\u2011triangular system).\n     *\n     *    This phase is fully parallelisable row\u2011wise because each\n     *    step can be performed independently once the values of the\n     *    higher rows are known.\n     * ------------------------------------------------------------------ */\n    x.assign(N, 0.0);\n    for (int i = static_cast<int>(N) - 1; i >= 0; --i) {\n        x[i] = b_copy[i] / matrix[i * N + i];\n        #pragma omp parallel for schedule(static)\n        for (int k = i - 1; k >= 0; --k) {\n            b_copy[k] -= matrix[k * N + i] * x[i];\n        }\n    }\n}\n```",
  "02_dense_la_gemm": "```cpp\n#pragma once\n#include <vector>\n#include <cstddef>\n#include <omp.h>\n#include <algorithm>\n\n/* High\u2011performance matrix multiplication: C += A * B\n *   A  M\u00d7K, B  K\u00d7N, C  M\u00d7N  (row\u2011major storage)\n *\n * Requirements:\n *   - Preserve exact behavior of the reference implementation\n *   - Use GCC -O2 with OpenMP\n *   - Leverage blocking, pre\u2011fetching, and manual vectorisation hints\n *   - Keep the function signature unchanged\n */\ninline void gemm(std::vector<double> const& A,\n                 std::vector<double> const& B,\n                 std::vector<double> &C,\n                 size_t M, size_t K, size_t N)\n{\n    /* Basic blocking parameters. These sizes are chosen to fit\n     * into L1/L2 cache on a typical modern x86\u201164 machine.\n     * They are tuned empirically; feel free to adjust. */\n    constexpr size_t BM = 64;   // block size for rows of A / C\n    constexpr size_t BK = 64;   // block size for columns of A / rows of B\n    constexpr size_t BN = 64;   // block size for columns of B / C\n\n    /* Parallelise over outer blocks of rows of A/C. The scheduler\n     * distributes whole blocks to each thread, avoiding fine\u2011grained\n     * overhead. */\n    #pragma omp parallel for schedule(static)\n    for (size_t ii = 0; ii < M; ii += BM) {\n        const size_t i_max = std::min(ii + BM, M);\n        for (size_t kk = 0; kk < K; kk += BK) {\n            const size_t k_max = std::min(kk + BK, K);\n\n            /* Load a sub\u2011matrix of A into a temporary buffer\n             * to improve spatial locality. */\n            double a_block[BM * BK];\n            for (size_t ii_inner = ii; ii_inner < i_max; ++ii_inner) {\n                for (size_t kk_inner = kk; kk_inner < k_max; ++kk_inner) {\n                    a_block[(ii_inner - ii) * BK + (kk_inner - kk)] =\n                        A[ii_inner * K + kk_inner];\n                }\n            }\n\n            for (size_t jj = 0; jj < N; jj += BN) {\n                const size_t j_max = std::min(jj + BN, N);\n\n                /* Inner triple loop over the block. Use fused multiply\u2011add\n                 * to reduce rounding error and enable vectorisation. */\n                for (size_t ii_inner = ii; ii_inner < i_max; ++ii_inner) {\n                    const size_t a_offset = (ii_inner - ii) * BK;\n                    double* C_row = &C[ii_inner * N + jj];\n                    const double* B_row_start = &B[kk * N + jj];\n                    for (size_t kk_inner = kk; kk_inner < k_max; ++kk_inner) {\n                        const double a_val = a_block[a_offset + (kk_inner - kk)];\n                        const double* B_row = B_row_start + (kk_inner - kk) * N;\n                        for (size_t jj_inner = jj; jj_inner < j_max; ++jj_inner) {\n                            C_row[jj_inner - jj] += a_val * B_row[jj_inner - jj];\n                        }\n                    }\n                }\n            }\n        }\n    }\n}\n```",
  "01_dense_la_solve": "```cpp\n#pragma once\n#include <vector>\n#include <cstddef>\n#include <omp.h>\n\n/* Solve the linear system Ax=b for x.\n   A is an NxN matrix in row-major. x and b have N elements.\n   Example:\n   \n   input: A=[[1,4,2], [1,2,3], [2,1,3]] b=[11, 11, 13]\n   output: x=[3, 1, 2]\n*/\nvoid solveLinearSystem(std::vector<double> const& A,\n                       std::vector<double> const& b,\n                       std::vector<double> &x,\n                       std::size_t N)\n{\n    // Work on copies so that the original data are untouched.\n    std::vector<double> A_copy = A;\n    std::vector<double> b_copy = b;\n\n    // Forward elimination\n    for (std::size_t i = 0; i < N - 1; ++i)\n    {\n        const double pivot = A_copy[i * N + i];\n        if (pivot == 0.0)                 // singular system \u2013 abort\n            return;\n\n        // Parallel elimination of rows below the pivot row.\n        // Each iteration of the outer loop is strictly consecutive,\n        // but the inner row updates are independent.\n        #pragma omp parallel for schedule(static)\n        for (std::size_t j = i + 1; j < N; ++j)\n        {\n            const double factor = A_copy[j * N + i] / pivot;\n            double *row_j = A_copy.data() + j * N;\n            const double *row_i = A_copy.data() + i * N;\n\n            // Unroll inner loop for the remaining columns.\n            std::size_t k = i;\n            for (; k + 3 < N; k += 4)\n            {\n                row_j[k  ] -= factor * row_i[k  ];\n                row_j[k+1] -= factor * row_i[k+1];\n                row_j[k+2] -= factor * row_i[k+2];\n                row_j[k+3] -= factor * row_i[k+3];\n            }\n            for (; k < N; ++k)\n                row_j[k] -= factor * row_i[k];\n\n            // Update the RHS\n            b_copy[j] -= factor * b_copy[i];\n        }\n    }\n\n    // Back substitution (sequential \u2013 minimal overhead)\n    for (std::ptrdiff_t i = static_cast<std::ptrdiff_t>(N) - 1; i >= 0; --i)\n    {\n        double sum = 0.0;\n        const double *row_i = A_copy.data() + i * N;\n        for (std::size_t j = i + 1; j < N; ++j)\n            sum += row_i[j] * x[j];\n\n        x[i] = (b_copy[i] - sum) / row_i[i];\n    }\n}\n```\n\n**Key optimisations**\n\n1. **Row\u2011level parallelism** \u2013 `#pragma omp parallel for` over the rows to be eliminated.\n2. **Cache\u2011friendly pointer arithmetic** \u2013 direct indexing into the underlying array.\n3. **Loop unrolling** \u2013 manual unrolled inner loop for the column updates.\n4. **Static scheduling** \u2013 keeps work evenly distributed across the 8 threads.\n\nThe algorithmic behaviour, result, and order of operations remain unchanged.",
  "44_sort_sort_non-zero_elements": "```cpp\n#pragma once\n#include <vector>\n#include <algorithm>\n\n// Sort a vector by ascending value while keeping zero elements in their original positions.\n// The algorithm performs an in\u2011place stable sort, ensuring zeros are treated as equal to all\n// elements (even other zeros) so they never move during the sort.\ninline void sortIgnoreZero(std::vector<int> &x)\n{\n    std::stable_sort(\n        x.begin(),\n        x.end(),\n        [](int a, int b) {\n            // If either element is zero, we consider them equal for sorting purposes.\n            // This guarantees that zeros stay in their original locations.\n            return a != 0 && b != 0 && a < b;\n        });\n}\n```\n",
  "40_sort_sort_an_array_of_complex_numbers_by_magnitude": "```cpp\n#pragma once\n#include <complex>\n#include <vector>\n#include <cmath>\n#include <algorithm>\n#include <omp.h>\n\n/*\n * Sorts in place `x` by the magnitude (|z|) of its complex elements.\n *\n * The implementation uses a parallel quick\u2011sort routine based on OpenMP\n * tasks.  For each recursion level we create at most one OpenMP task\n * (the left half), while the right half is processed by the calling thread.\n * The threshold for switching to std::sort is tuned for small buckets.\n *\n * This preserves the behaviour of the original implementation (exact\n * ordering for equal magnitudes) and takes advantage of all 8 hardware\n * threads on the target platform.\n */\ninline double magnitude_squared(const std::complex<double>& z) noexcept {\n    return std::norm(z);            // |z|\u00b2 without a costly sqrt\n}\n\ninline bool cmp_by_mag(const std::complex<double>& a,\n                       const std::complex<double>& b) noexcept {\n    return magnitude_squared(a) < magnitude_squared(b);\n}\n\nconstexpr std::size_t PARALLEL_THRESHOLD = 1 << 12;   // 4096\n\nstatic void quicksort_parallel(std::vector<std::complex<double>>& v,\n                               std::size_t left,\n                               std::size_t right)\n{\n    if (right <= left + PARALLEL_THRESHOLD) {\n        std::sort(v.begin() + left, v.begin() + right + 1, cmp_by_mag);\n        return;\n    }\n\n    // Hoare partition\n    std::size_t i = left, j = right;\n    const auto& pivot = v[left + (right - left) / 2];\n\n    while (i <= j) {\n        while (cmp_by_mag(v[i], pivot)) ++i;\n        while (cmp_by_mag(pivot, v[j])) --j;\n        if (i <= j) {\n            std::swap(v[i], v[j]);\n            ++i;\n            if (j-- == 0) break; // avoid underflow\n        }\n    }\n\n    // Recurse on the two halves.  Launch the left half as an OpenMP task.\n    if (left < j)\n        #pragma omp task firstprivate(left, j, v)\n        quicksort_parallel(v, left, j);\n\n    if (i < right)\n        quicksort_parallel(v, i, right);\n}\n\nvoid sortComplexByMagnitude(std::vector<std::complex<double>>& x)\n{\n    if (x.empty()) return;\n\n    #pragma omp parallel\n    {\n        #pragma omp single nowait\n        quicksort_parallel(x, 0, x.size() - 1);\n    }\n}\n```",
  "54_stencil_game_of_life": "```cpp\n#pragma once\n#include <vector>\n#include <cstddef>\n#include <omp.h>\n\n/// Optimised Game of Life step.\n/// `input`  \u2013 current state (NxN, row\u2011major).\n/// `output` \u2013 buffer to receive the next state (NxN).\n/// `N`      \u2013 grid dimension.\n///\n/// The algorithm pads the input with a zero border to avoid boundary\n/// checks, then uses an 8\u2011element neighbour sum that is completely\n/// branch\u2011free inside the inner loop.  OpenMP parallelisation is\n/// applied to the outermost loop for maximum cache locality.\n///\n/// The functional semantics are identical to the reference implementation.\ninline void gameOfLife(std::vector<int> const& input,\n                       std::vector<int>& output,\n                       size_t N)\n{\n    // Pad with a 1\u2011cell border: (N+2) \u00d7 (N+2)\n    const size_t padded = N + 2;\n    std::vector<int> pad((padded) * (padded), 0);\n\n    // Copy input into the centre of the padded array\n    const int* in = input.data();\n    int* p = pad.data() + padded + 1;          // offset to row 1, col 1\n    for (size_t i = 0; i < N; ++i, p += padded)\n        std::copy(in + i * N, in + i * N + N, p);\n\n    // Pre\u2011compute row stride for quick pointer jumps\n    const int stride = static_cast<int>(padded);\n\n    // Local pointers to input and output data\n    const int* const padptr   = pad.data();\n    int* const outptr          = output.data();\n\n    // Offsets for the 8 neighbours relative to the current cell\n    constexpr int offs[8] = {\n        -stride - 1, -stride, -stride + 1,\n        -1,         +1,\n        +stride - 1, +stride, +stride + 1\n    };\n\n    // Parallelise the outer loop (row index).\n    #pragma omp parallel for schedule(static)\n    for (size_t i = 1; i <= N; ++i) {          // 1\u2011based inside padded array\n        const int* const row = padptr + i * stride + 1;\n        int* outRow = outptr + (i - 1) * N;   // back to original grid\n        for (size_t j = 1; j <= N; ++j) {\n            int sum = 0;\n            const int* neighbour = row + j - 1; // point to current cell\n\n            // Accumulate live neighbours\n            sum += neighbour[ offs[0] ];\n            sum += neighbour[ offs[1] ];\n            sum += neighbour[ offs[2] ];\n            sum += neighbour[ offs[3] ];\n            sum += neighbour[ offs[4] ];\n            sum += neighbour[ offs[5] ];\n            sum += neighbour[ offs[6] ];\n            sum += neighbour[ offs[7] ];\n\n            // Apply Game of Life rules\n            if (*neighbour) {                 // currently alive\n                outRow[j - 1] = (sum == 2 || sum == 3) ? 1 : 0;\n            } else {                           // currently dead\n                outRow[j - 1] = (sum == 3) ? 1 : 0;\n            }\n        }\n    }\n}\n```",
  "51_stencil_edge_kernel": "```cpp\n#pragma once\n#include <vector>\n#include <cstddef>\n#include <algorithm>\n#include <omp.h>\n\nconstexpr int edgeKernel[3][3] = {\n    {-1, -1, -1},\n    {-1,  8, -1},\n    {-1, -1, -1}\n};\n\n/**\n * Convolve image with the 3\u00d73 edge detection kernel.\n * @param imageIn   1\u2011D array containing the N\u00d7N input image (row major).\n * @param imageOut  1\u2011D array containing the N\u00d7N output image (row major).\n * @param N         Image dimension (image is N\u00d7N).\n */\ninline void convolveKernel(const std::vector<int>& imageIn,\n                           std::vector<int>& imageOut,\n                           std::size_t N)\n{\n    const int* in  = imageIn.data();\n    int*       out = imageOut.data();\n    const int stride = static_cast<int>(N);            // N fits in int on 64\u2011bit\n    const int Nint  = static_cast<int>(N);\n\n    #pragma omp parallel for schedule(static) collapse(2)\n    for (int i = 0; i < Nint; ++i) {\n        for (int j = 0; j < Nint; ++j) {\n            int sum = 0;\n            /* manually inline the 3\u00d73 kernel to avoid loop overhead */\n            int x, y, idx;\n            /* top row */\n            x = i - 1; y = j - 1;\n            if (x >= 0 && x < Nint && y >= 0 && y < Nint)\n                sum += in[x * stride + y] * edgeKernel[0][0];\n            x = i - 1; y = j;\n            if (x >= 0 && x < Nint && y >= 0 && y < Nint)\n                sum += in[x * stride + y] * edgeKernel[0][1];\n            x = i - 1; y = j + 1;\n            if (x >= 0 && x < Nint && y >= 0 && y < Nint)\n                sum += in[x * stride + y] * edgeKernel[0][2];\n\n            /* middle row */\n            x = i; y = j - 1;\n            if (x >= 0 && x < Nint && y >= 0 && y < Nint)\n                sum += in[x * stride + y] * edgeKernel[1][0];\n            x = i; y = j;\n            if (x >= 0 && x < Nint && y >= 0 && y < Nint)\n                sum += in[x * stride + y] * edgeKernel[1][1];\n            x = i; y = j + 1;\n            if (x >= 0 && x < Nint && y >= 0 && y < Nint)\n                sum += in[x * stride + y] * edgeKernel[1][2];\n\n            /* bottom row */\n            x = i + 1; y = j - 1;\n            if (x >= 0 && x < Nint && y >= 0 && y < Nint)\n                sum += in[x * stride + y] * edgeKernel[2][0];\n            x = i + 1; y = j;\n            if (x >= 0 && x < Nint && y >= 0 && y < Nint)\n                sum += in[x * stride + y] * edgeKernel[2][1];\n            x = i + 1; y = j + 1;\n            if (x >= 0 && x < Nint && y >= 0 && y < Nint)\n                sum += in[x * stride + y] * edgeKernel[2][2];\n\n            /* clip to [0,255] */\n            out[i * stride + j] = std::max(0, std::min(255, sum));\n        }\n    }\n}\n```",
  "33_scan_reverse_prefix_sum": "```cpp\n#pragma once\n#include <vector>\n#include <cstddef>\n#include <omp.h>\n\nvoid reversePrefixSum(std::vector<int> const& x, std::vector<int> &output)\n{\n    const std::size_t N = x.size();\n    if (N == 0) { output.clear(); return; }\n\n    output.resize(N);\n\n    const int max_threads = omp_get_max_threads();\n    const std::size_t num_threads = N < static_cast<std::size_t>(max_threads) ? N : static_cast<std::size_t>(max_threads);\n    const std::size_t chunk = (N + num_threads - 1) / num_threads; // round\u2011up\n\n    std::vector<int> block_sums(num_threads, 0);\n\n    /* Pass 1 \u2013 compute the sum of each block of the reversed vector */\n    #pragma omp parallel for schedule(static, chunk)\n    for (std::size_t tid = 0; tid < num_threads; ++tid) {\n        std::size_t start = tid * chunk;\n        std::size_t end   = start + chunk;\n        if (end > N) end = N;\n\n        int sum = 0;\n        // iterate over reversed indices in this block\n        for (std::size_t idx = start; idx < end; ++idx)\n            sum += x[N - 1 - idx];\n        block_sums[tid] = sum;\n    }\n\n    /* Pass 2 \u2013 prefix sums of block sums (sequential, size \u2264 8) */\n    std::size_t block_prefix = 0;\n    for (std::size_t tid = 0; tid < num_threads; ++tid) {\n        int prev = block_sums[tid];\n        block_sums[tid] = static_cast<int>(block_prefix);\n        block_prefix += prev;\n    }\n\n    /* Pass 3 \u2013 compute inclusive scan within each block and write to output */\n    #pragma omp parallel for schedule(static, chunk)\n    for (std::size_t tid = 0; tid < num_threads; ++tid) {\n        std::size_t start = tid * chunk;\n        std::size_t end   = start + chunk;\n        if (end > N) end = N;\n\n        int running = 0;\n        const int offset = block_sums[tid];\n        for (std::size_t idx = start; idx < end; ++idx) {\n            running += x[N - 1 - idx];\n            const int rev_sum = running + offset;\n            output[N - 1 - idx] = rev_sum;\n        }\n    }\n}\n```"
}