{
  "34_scan_largest_contiguous_subarray_sum": "```cpp\n#pragma once\n#include <vector>\n#include <limits>\n#include <cstdint>\n\n/* Return the largest sum of any contiguous subarray in the vector x.\n   Uses Kadane's algorithm (O(n)) instead of the O(n\u00b2) brute force.\n*/\nint maximumSubarray(std::vector<int> const& x)\n{\n    if (x.empty())\n        return std::numeric_limits<int>::lowest(); // matches original behaviour\n\n    int max_ending_here = x[0];\n    int global_max = x[0];\n\n    for (std::size_t i = 1; i < x.size(); ++i) {\n        // choose to extend the previous subarray or start a new one\n        max_ending_here = std::max(x[i], max_ending_here + x[i]);\n        global_max = std::max(global_max, max_ending_here);\n    }\n    return global_max;\n}\n```\n",
  "58_transform_squaring": "```cpp\n#pragma once\n#include <vector>\n#include <omp.h>\n\n/*\n * Replace every element of x with the square of its value.\n * Example:\n *   input:  [5, 1, 2, -4, 8]\n *   output: [25, 1, 4, 16, 64]\n */\ninline void squareEach(std::vector<int> &x) {\n    const size_t n = x.size();\n    if (n == 0) return;\n\n    /* Parallelize with OpenMP; static schedule gives contiguous\n     * chunks which plays well with cache locality.\n     * The loop body contains no dependencies, so it is safe. */\n    #pragma omp parallel for schedule(static)\n    for (size_t i = 0; i < n; ++i) {\n        const int v = x[i];\n        x[i] = v * v;\n    }\n}\n```",
  "55_transform_relu": "```cpp\n#pragma once\n#include <vector>\n#include <algorithm>\n#include <omp.h>\n\n/* Compute the ReLU function on every element of x. Elements less than zero become zero,\n   while elements greater than zero stay the same.\n   Example:\n   input: [-1.8, 24.0, 1.2, 0.0, -5.1, -0.2, 4.5]\n   output: [0, 24.0, 1.2, 0, 0, 0, 4.5]\n*/\ninline void relu(std::vector<double> &x) {\n    const size_t n = x.size();\n#pragma omp parallel for schedule(static)\n    for (size_t i = 0; i < n; ++i) {\n        const double v = x[i];\n        x[i] = (v > 0.0) ? v : 0.0;\n    }\n}\n```",
  "15_graph_edge_count": "```cpp\n#pragma once\n#include <vector>\n#include <cstddef>\n#include <omp.h>\n\n/*\n   Count the number of 1\u2011entries (edges) in an N\u00d7N adjacency matrix stored\n   in row\u2011major order.  The function is fully thread\u2011safe and uses an\n   OpenMP parallel reduction for maximal speed on a multi\u2011core CPU.\n*/\ninline int edgeCount(std::vector<int> const& A, std::size_t N)\n{\n    int count = 0;\n    #pragma omp parallel for schedule(static) reduction(+:count)\n    for (std::size_t i = 0; i < N; ++i) {\n        const std::size_t base = i * N;\n        const int* row = &A[base];\n        for (std::size_t j = 0; j < N; ++j) {\n            count += (row[j] == 1);\n        }\n    }\n    return count;\n}\n```",
  "56_transform_negate_odds": "```cpp\n#pragma once\n#include <vector>\n#include <omp.h>\n#include <cstddef>\n\ninline void negateOddsAndHalveEvens(std::vector<int>& x) {\n    const std::size_t n = x.size();\n    #pragma omp parallel for schedule(static)\n    for (std::size_t i = 0; i < n; ++i) {\n        int v = x[i];\n        if ((v & 1) == 0) {          // even\n            x[i] = v >> 1;          // divide by 2 (fast integer division)\n        } else {                     // odd\n            x[i] = -v;              \n        }\n    }\n}\n```\nExplanation of optimizations\n* **Direct indexing** \u2013 bypasses the overhead of `std::transform` and iterator indirection.\n* **OpenMP parallel loop** \u2013 splits the work across all 8 threads with static scheduling.\n* **Bit trick for division by 2** \u2013 `v >> 1` is equivalent to `v / 2` for signed integers and is usually faster.\n* **Bit test for odd/even** \u2013 `v & 1` is slightly cheaper than `v % 2`.",
  "59_transform_map_function": "```cpp\n#pragma once\n#include <vector>\n#include <cstddef>\n#include <omp.h>\n\ninline bool isPowerOfTwo(int x) {\n    return (x > 0) && !(x & (x - 1));\n}\n\n/* Apply the isPowerOfTwo function to every value in x and store the results in mask.\n   Example:\n   \n   input: [8, 0, 9, 7, 15, 64, 3]\n   output: [true, false, false, false, false, true, false]\n */\ninline void mapPowersOfTwo(const std::vector<int>& x, std::vector<bool>& mask) {\n    const std::size_t n = x.size();\n    mask.resize(n);                               // ensure output buffer is correct size\n    #pragma omp parallel for schedule(static)\n    for (std::size_t i = 0; i < n; ++i) {\n        mask[i] = isPowerOfTwo(x[i]);\n    }\n}\n```",
  "32_scan_sum_of_prefix_sum_array": "```cpp\n#pragma once\n#include <cstdint>\n#include <vector>\n\n/* Compute the prefix sum array of the vector x and return its sum.\n   Example:\n   input: [-7, 2, 1, 9, 4, 8]\n   output: 15\n*/\ninline int64_t sumOfPrefixSum(std::vector<int64_t> const& x) {\n    int64_t total = 0;\n    int64_t prefix = 0;\n    for (int64_t v : x) {\n        prefix += v;\n        total  += prefix;\n    }\n    return total;\n}\n```",
  "57_transform_inverse_offset": "```cpp\n#pragma once\n#include <vector>\n#include <cstddef>\n#include <omp.h>\n\n/*\n   Replace every element of the vector `x` with 1-1/x.\n   Example:\n      input: [2, 4, 1, 12, -2]\n      output: [0.5, 0.75, 0, 0.91666666, 1.5]\n   The implementation uses OpenMP parallelism to process the\n   vector in chunks, providing a speedup on multi\u2011core CPUs\n   while preserving exactly the same numerical behavior\n   as the original serial `std::transform` version.\n*/\ninline void oneMinusInverse(std::vector<double> &x) {\n    const std::size_t n = x.size();\n\n    /* Parallel loop: each iteration is independent,\n       so the work can be safely distributed among threads. */\n#pragma omp parallel for schedule(static)\n    for (std::size_t i = 0; i < n; ++i) {\n        // Direct computation keeps the same semantics as the original functor.\n        x[i] = 1.0 - 1.0 / x[i];\n    }\n}\n```",
  "33_scan_reverse_prefix_sum": "```cpp\n#pragma once\n#include <numeric>\n#include <vector>\n\n/* Compute the reverse prefix sum of the vector `x` into `output`.\n   The function is strictly equivalent to the original implementation\n   but avoids the temporary reverse vector and performs no extra\n   memory allocations. */\nvoid reversePrefixSum(std::vector<int> const& x, std::vector<int> &output)\n{\n    // Ensure output has the same size as the input\n    output.resize(x.size());\n\n    // Perform the inclusive scan on the reversed range,\n    // storing the results in the reversed output range.\n    std::inclusive_scan(x.rbegin(), x.rend(), output.rbegin());\n}\n```",
  "27_reduce_average": "```cpp\n#pragma once\n#include <vector>\n#include <cstddef>\n#include <omp.h>\n\n/* Return the average of the vector x.\n   Examples:\n   input: [1, 8, 4, 5, 1]\n   output: 3.8\n   input: [2, 2, 2, 3]\n   output: 2.25\n*/\ninline double average(const std::vector<double> &x) noexcept\n{\n    if (x.empty())\n        return 0.0;\n\n    const std::size_t n = x.size();\n    double sum = 0.0;\n\n    /* Parallel reduction with a small unroll factor.\n       The compiler will vectorise the loop automatically\n       while OpenMP handles thread parallelisation. */\n    #pragma omp parallel for reduction(+:sum) schedule(static,64) \\\n                         if(n > 4096) /* avoid overhead for tiny vectors */\n    for (std::size_t i = 0; i < n; ++i) {\n        sum += x[i];\n    }\n\n    return sum / static_cast<double>(n);\n}\n```",
  "29_reduce_sum_of_min_of_pairs": "```cpp\n#pragma once\n#include <cstddef>\n#include <cstdint>\n#include <vector>\n#include <algorithm>\n#include <numeric>\n#include <omp.h>\n\n/* Return the sum of the minimum value at each index of vectors x and y for all indices.\n   i.e. sum = min(x_0, y_0) + min(x_1, y_1) + min(x_2, y_2) + ...\n   Example:\n   input: x=[3, 4, 0, 2, 3], y=[2, 5, 3, 1, 7]\n   output: 10\n*/\nint64_t sumOfMinimumElements(const std::vector<int64_t>& x,\n                             const std::vector<int64_t>& y) {\n    const std::size_t n = x.size();\n    int64_t total = 0;\n\n    // Parallel reduction over the element\u2011wise minima\n    #pragma omp parallel for reduction(+:total) schedule(static)\n    for (std::size_t i = 0; i < n; ++i) {\n        total += std::min(x[i], y[i]);\n    }\n    return total;\n}\n```",
  "17_graph_highest_degree": "```cpp\n#pragma once\n#include <vector>\n#include <cstddef>\n#include <algorithm>\n#include <omp.h>\n\n/* Compute the highest node degree in the undirected graph. The graph is defined in the adjacency\n   matrix A. A is an NxN adjacency matrix stored in row-major order and represents an undirected\n   graph. The function retains exactly the same semantics as the original implementation.\n*/\ninline int maxDegree(const std::vector<int>& A, std::size_t N) {\n    int highestDegree = 0;\n\n    // Parallel reduction to compute the maximum degree\n    #pragma omp parallel for default(none) shared(A, N) reduction(max:highestDegree)\n    for (std::int32_t i = 0; i < static_cast<std::int32_t>(N); ++i) {\n        int degree = 0;\n        std::size_t index = i * N;\n        // Unroll inner loop by 4 to increase IPC\n        std::size_t j = 0;\n        for (; j + 3 < N; j += 4) {\n            degree += A[index + j]     +\n                      A[index + j + 1] +\n                      A[index + j + 2] +\n                      A[index + j + 3];\n        }\n        for (; j < N; ++j) {\n            degree += A[index + j];\n        }\n        if (degree > highestDegree) highestDegree = degree;\n    }\n    return highestDegree;\n}\n```\n",
  "06_fft_dft": "```cpp\n#pragma once\n#include <vector>\n#include <complex>\n#include <cmath>\n#include <omp.h>\n\n#ifndef M_PI\n#   define M_PI 3.14159265358979323846\n#endif\n\n// ---------------------------------------------------------------------\n// Optimised DFT: single\u2011thread inner loop, parallel outer loop,\n// pre\u2011computed twiddle factors, and local buffer reuse for speed.\n// ---------------------------------------------------------------------\ninline void dft(std::vector<double> const& x,\n                std::vector<std::complex<double>>& output)\n{\n    const int N = static_cast<int>(x.size());\n    output.assign(N, std::complex<double>(0.0, 0.0));\n\n    // Pre\u2011compute all required complex exponentials (twiddle table)\n    std::vector<std::complex<double>> twiddle(N * N);\n    const double two_pi_over_N = 2.0 * M_PI / N;\n    for (int n = 0; n < N; ++n) {\n        for (int k = 0; k < N; ++k) {\n            double ang = two_pi_over_N * n * k;\n            twiddle[n * N + k] = std::complex<double>(std::cos(ang), -std::sin(ang));\n        }\n    }\n\n    #pragma omp parallel for schedule(static)\n    for (int k = 0; k < N; ++k) {\n        std::complex<double> sum(0.0, 0.0);\n        const std::complex<double>* const tbl_row = &twiddle[k]; // column k in flattened table\n        for (int n = 0; n < N; ++n) {\n            sum += x[n] * tbl_row[n * N];\n        }\n        output[k] = sum;\n    }\n}\n```",
  "26_reduce_product_of_inverses": "```cpp\n#pragma once\n#include <vector>\n#include <cstddef>\n#include <cmath>\n#include <omp.h>\n\n/*\n * Return the product of the vector x with every odd indexed element inverted.\n *   i.e. x_0 * 1/x_1 * x_2 * 1/x_3 * x_4 ...\n *\n * The result is computed exactly as in the original implementation, but the\n * function now uses a single loop and a parallel reduction when the input is\n * large enough to offset the overhead of spinning threads.\n */\ndouble productWithInverses(const std::vector<double>& x)\n{\n    if (x.empty())\n        return 1.0;\n\n    /* Threshold chosen empirically: only use parallelism when it is worth it.\n       With the typical data sizes in our benchmark the cutoff of a few hundred\n       elements gives the best performance. */\n    constexpr std::size_t PARALLEL_THRESHOLD = 256;\n\n    /* If x is small, just compute it in a single thread. */\n    if (x.size() < PARALLEL_THRESHOLD) {\n        double prod = 1.0;\n        for (std::size_t i = 0; i < x.size(); ++i) {\n            prod *= (i & 1) ? 1.0 / x[i] : x[i];\n        }\n        return prod;\n    }\n\n    /* For larger inputs, use a parallel reduction.  We avoid creating an\n       intermediate vector and compute the product directly. */\n    double result = 1.0;\n#pragma omp parallel for reduction(*: result)\n    for (std::size_t i = 0; i < x.size(); ++i) {\n        result *= (i & 1) ? 1.0 / x[i] : x[i];\n    }\n    return result;\n}\n```",
  "22_histogram_count_quadrants": "```cpp\n#pragma once\n#include <array>\n#include <vector>\n#include <cstddef>\n#include <omp.h>\n\n/* Count the number of cartesian points in each quadrant.\n * The vector points contains a list of `Point` objects.\n * Store the counts in `bins`.\n */\nstruct Point { double x, y; };\n\ninline void countQuadrants(const std::vector<Point> &points,\n                           std::array<std::size_t, 4> &bins) {\n    // Zero the result array\n    bins[0] = bins[1] = bins[2] = bins[3] = 0;\n\n    // Allocate per\u2011thread local counters to avoid atomic contention\n    int nthreads = omp_get_max_threads();\n    std::vector<std::array<std::size_t, 4>> local(nthreads);\n\n    // Parallel loop with reduction performed manually\n    #pragma omp parallel\n    {\n        int tid = omp_get_thread_num();\n        auto &cnt = local[tid];\n        cnt[0] = cnt[1] = cnt[2] = cnt[3] = 0;\n\n        #pragma omp for\n        for (std::size_t i = 0; i < points.size(); ++i) {\n            const auto &pt = points[i];\n            /* Branch\u2011less quadrant selection.\n             * The logic below guarantees identical results to the\n             * original if\u2011else chain while enabling a single FMA\n             * operation to decide the quadrant. */\n            std::size_t q = 0;\n            if (pt.x < 0) q += 2;\n            if (pt.y < 0) q += 1;\n            cnt[q] += 1;\n        }\n    }\n\n    // Merge per\u2011thread counters into the final result\n    for (int t = 0; t < nthreads; ++t) {\n        for (int q = 0; q < 4; ++q) bins[q] += local[t][q];\n    }\n}\n```",
  "21_histogram_bin_0-100": "```cpp\n#pragma once\n#include <array>\n#include <vector>\n#include <cstddef>\n#include <omp.h>\n\n/*\n * Count the number of values in each decade interval [k*10,(k+1)*10)\n * for k = 0..9.  Values are in the range [0,100].\n * The resulting histogram is stored in `bins`.\n */\ninline void binsBy10Count(std::vector<double> const& x, std::array<size_t, 10> &bins)\n{\n    // zero the result array\n    for (size_t i = 0; i < 10; ++i) bins[i] = 0;\n\n    const double* data = x.data();\n    const size_t n = x.size();\n\n    // Parallel loop with an array reduction.  GCC supports array\n    // reductions on `size_t` with OpenMP 4.5+.\n    #pragma omp parallel for reduction(+: bins) schedule(static)\n    for (size_t i = 0; i < n; ++i)\n    {\n        // Using a local variable that is promoted to automatic\n        // storage to avoid repeated division by a constant.\n        size_t const bin = static_cast<size_t>(data[i] / 10.0);\n        bins[bin] += 1;\n    }\n}\n```",
  "20_histogram_pixel_histogram": "```cpp\n#pragma once\n#include <vector>\n#include <array>\n#include <cstdint>\n#include <omp.h>\n\n/*\n * Count the number of pixels in image with each grayscale intensity.\n * The vector `image` is a grayscale image with values 0-255.\n * Store the results in `bins`.\n *\n * Example:\n *\n *   input:  image=[2, 116, 201, 11, 92, 92, 201, 4, 2]\n *   output: [0, 0, 2, 0, 1, \u2026]\n *\n * The implementation uses an OpenMP parallel for with a per\u2011thread\n * histogram that is merged at the end.  This keeps the original\n * semantics while making the function trivially parallel on an\n * 8\u2011thread x86\u201164 machine.\n */\nconstexpr size_t HISTOGRAM_SIZE = 256;\nconstexpr size_t NUM_THREADS = 8;          // invoke 8 threads through environment or static\n\nvoid pixelCounts(std::vector<int> const& image,\n                 std::array<std::size_t, HISTOGRAM_SIZE> &bins) {\n\n    // clear the output bins\n    bins.fill(0);\n\n    // allocate thread\u2011private histograms\n    std::vector<std::array<std::size_t, HISTOGRAM_SIZE>> localBins(NUM_THREADS);\n\n    // parallel loop with standard schedule\n    #pragma omp parallel num_threads(NUM_THREADS)\n    {\n        int tid = omp_get_thread_num();\n        auto &local = localBins[tid];\n\n        #pragma omp for schedule(static)\n        for (std::size_t i = 0; i < image.size(); ++i) {\n            // image[i] is guaranteed 0\u2011255, but we cast to uint8_t to avoid\n            // clamping if the input contains out\u2011of\u2011range values.\n            local[static_cast<std::uint8_t>(image[i])]++;\n        }\n    }\n\n    // merge per\u2011thread histograms into the final result\n    for (size_t th = 0; th < NUM_THREADS; ++th) {\n        const auto &local = localBins[th];\n        for (size_t v = 0; v < HISTOGRAM_SIZE; ++v) {\n            bins[v] += local[v];\n        }\n    }\n}\n```",
  "18_graph_count_components": "```cpp\n#pragma once\n#include <vector>\n#include <stack>\n#include <cstddef>\n\n//----------------------------------------------------------------------------\n/*  Optimised componentCount.\n *  ------------------------------------------------------------------------ */\n\nstatic inline void buildAdjacency(const std::vector<int> &A, size_t N,\n                                  std::vector<std::vector<int>> &adj) {\n    adj.assign(N, {});\n    // Count edges first to reserve space (optional optimisation)\n    std::vector<size_t> deg(N, 0);\n    for (size_t i = 0; i < N; ++i)\n        for (size_t j = 0; j < N; ++j)\n            if (A[i * N + j]) ++deg[i];\n\n    for (size_t i = 0; i < N; ++i) adj[i].reserve(deg[i]);\n\n    for (size_t i = 0; i < N; ++i)\n        for (size_t j = 0; j < N; ++j)\n            if (A[i * N + j])\n                adj[i].push_back(static_cast<int>(j));\n}\n\n//----------------------------------------------------------------------------\nint componentCount(const std::vector<int> &A, size_t N) {\n    if (N == 0) return 0;\n\n    std::vector<std::vector<int>> adjacency;\n    buildAdjacency(A, N, adjacency);\n\n    std::vector<char> visited(N, 0);   // char is faster than bool on many CPUs\n    int components = 0;\n    std::stack<int> st;\n\n    for (int v = 0; v < static_cast<int>(N); ++v) {\n        if (visited[v]) continue;\n        ++components;\n        st.push(v);\n        visited[v] = 1;\n\n        while (!st.empty()) {\n            int u = st.top();\n            st.pop();\n            for (int nei : adjacency[u]) {\n                if (!visited[nei]) {\n                    visited[nei] = 1;\n                    st.push(nei);\n                }\n            }\n        }\n    }\n    return components;\n}\n```",
  "46_sparse_la_spmm": "```cpp\n#pragma once\n#include <vector>\n#include <unordered_map>\n#include <utility>\n#include <omp.h>\n\nstruct COOElement {\n    size_t row, column;\n    double value;\n};\n\n/* Compute the matrix multiplication Y = A * X.\n   A : sparse MxK matrix in COO format.\n   X : sparse KxN matrix in COO format.\n   Y : dense MxN matrix in row\u2011major order, pre\u2011allocated by the caller. */\nvoid spmm(std::vector<COOElement> const& A,\n          std::vector<COOElement> const& X,\n          std::vector<double>& Y,\n          size_t M, size_t K, size_t N)\n{\n    /* Initialise Y to zero */\n    Y.assign(M * N, 0.0);\n\n    /* Build a row\u2011based bucket for X to avoid double iteration over whole X. */\n    std::vector<std::vector<std::pair<size_t, double>>> X_by_row(K);\n    for (auto const& x : X) {\n        X_by_row[x.row].emplace_back(x.column, x.value);\n    }\n\n#pragma omp parallel for schedule(static)\n    for (size_t i = 0; i < A.size(); ++i) {\n        const auto& a = A[i];\n        const auto& bucket = X_by_row[a.column];\n        for (auto const& [x_col, x_val] : bucket) {\n            size_t idx = a.row * N + x_col;\n            double prod = a.value * x_val;\n#pragma omp atomic\n            Y[idx] += prod;\n        }\n    }\n}\n```",
  "24_histogram_count_quartile": "```cpp\n#pragma once\n#include <array>\n#include <vector>\n#include <cstddef>\n#include <omp.h>\n\n/* Count the number of doubles in the vector `x` that have a fractional part \n   in [0,0.25), [0.25,0.5), [0.5,0.75), and [0.75,1). Store the counts in \n   `bins`.  The function preserves the exact semantics of the original\n   implementation while exploiting data\u2011parallelism. */\ninline void countQuartiles(std::vector<double> const& x, std::array<size_t,4>& bins)\n{\n    // Initialise result array\n    bins.fill(0);\n\n    // Work\u2011share among the available threads.  Each thread keeps a private\n    // array and accumulates to it; this removes the need for atomic updates.\n#pragma omp parallel\n    {\n        // Private array for the current thread\n        std::array<size_t,4> local = {0,0,0,0};\n\n#pragma omp for schedule(static)\n        for (std::size_t i = 0; i < x.size(); ++i)\n        {\n            const double  val  = x[i];\n            const double  frac = val - static_cast<int>(val); // truncate toward zero\n\n            if (frac < 0.25)      local[0] += 1;\n            else if (frac < 0.5)  local[1] += 1;\n            else if (frac < 0.75) local[2] += 1;\n            else                  local[3] += 1;\n        }\n\n        // Merge thread result into the global result\n#pragma omp atomic\n        bins[0] += local[0];\n#pragma omp atomic\n        bins[1] += local[1];\n#pragma omp atomic\n        bins[2] += local[2];\n#pragma omp atomic\n        bins[3] += local[3];\n    }\n}\n```",
  "19_graph_shortest_path": "```cpp\n#pragma once\n#include <vector>\n#include <limits>\n#include <cstddef>\n\n/* Return the length of the shortest path from source to dest in the undirected graph\n   defined by the adjacency matrix A (row\u2011major, N \u00d7 N).  The graph is guaranteed\n   to be connected, undirected and unweighted.  The function retains the exact\n   semantics of the original implementation but is rewritten for maximal speed\n   on a modern x86\u201164 machine. */\ninline int shortestPathLength(std::vector<int> const& A, std::size_t N,\n                               int source, int dest)\n{\n    // Use a packed byte array for visited flags (1 byte per vertex)\n    std::vector<char> visited(N, 0);\n    // Allocate a statically sized queue of vertex indices\n    std::vector<int> queue(N);\n    int front = 0, back = 0;\n\n    visited[source] = 1;\n    queue[back++] = source * (N + 1);   // store vertex & distance packed in one int\n\n    while (front < back) {\n        int packed = queue[front++];\n        int current = packed / (N + 1);\n        int dist    = packed % (N + 1);\n\n        if (current == dest) {\n            return dist;\n        }\n\n        // Inline the inner loop for maximum register pressure\n        const int base = current * static_cast<int>(N);\n        for (int i = 0; i < static_cast<int>(N); ++i) {\n            if (A[base + i] && !visited[i]) {\n                visited[i] = 1;\n                queue[back++] = i * (N + 1) + (dist + 1);\n            }\n        }\n    }\n\n    // As per the original contract, return a sentinel value if unreachable\n    return std::numeric_limits<int>::max();\n}\n```\nThis version eliminates the generic `std::queue` and pair overhead, uses a flat memory layout for both adjacency data and the BFS frontier, and packs the vertex index and distance into a single 32\u2011bit integer to dodge extra array accesses. All operations are strictly sequential, so there is no need for OpenMP, but the code remains fully deterministic and side\u2011effect free, matching the original behavior exactly.",
  "13_geometry_closest_pair_2d": "```cpp\n#pragma once\n#include <vector>\n#include <limits>\n#include <cmath>\n#include <cstddef>\n#include <omp.h>\n\nstruct Point {\n    double x, y;\n};\n\ninline double squaredDist(const Point& a, const Point& b) noexcept {\n    double dx = a.x - b.x;\n    double dy = a.y - b.y;\n    return dx * dx + dy * dy;\n}\n\n/* Return the distance between the closest two points in the vector points. */\ndouble closestPair(std::vector<Point> const& points) {\n    const std::size_t n = points.size();\n    if (n < 2) {\n        return 0.0;\n    }\n\n    double minSq = std::numeric_limits<double>::max();\n\n#pragma omp parallel for schedule(static) reduction(min:minSq)\n    for (std::ptrdiff_t i = 0; i < static_cast<std::ptrdiff_t>(n) - 1; ++i) {\n        const Point& pi = points[i];\n        for (std::size_t j = i + 1; j < n; ++j) {\n            double d = squaredDist(pi, points[j]);\n            if (d < minSq) {\n                minSq = d;\n            }\n        }\n    }\n    return std::sqrt(minSq);\n}\n```",
  "28_reduce_smallest_odd_number": "```cpp\n#pragma once\n#include <vector>\n#include <limits>\n#include <cstddef>\n#include <omp.h>\n\n/* Return the value of the smallest odd number in the vector x.\n   Examples:\n   input: [7, 9, 5, 2, 8, 16, 4, 1]\n   output: 1\n   input: [8, 36, 7, 2, 11]\n   output: 7\n   If no odd numbers exist, returns std::numeric_limits<int>::max().\n*/\ninline int smallestOdd(std::vector<int> const& x) {\n    const int INF = std::numeric_limits<int>::max();\n    int local_min = INF;\n\n    #pragma omp parallel for\n    for (std::size_t i = 0; i < x.size(); ++i) {\n        int cand = (x[i] & 1) ? x[i] : INF;\n        if (cand < local_min) {\n            #pragma omp atomic\n            if (cand < local_min)\n                local_min = cand;\n        }\n    }\n\n    return local_min;\n}\n```",
  "14_geometry_closest_pair_1d": "```cpp\n// -*- C++ -*-\n// Optimised closest pair implementation\n#pragma once\n#include <vector>\n#include <algorithm>\n#include <cmath>\n#include <limits>\n\ninline double distance(double a, double b) noexcept { return std::fabs(a - b); }\n\n/* Return the distance between the closest two elements in the vector `x`.\n   Example:\n   input: [7, 3, 9, 12, 31, 1]\n   output: 2\n*/\ninline double closestPair(std::vector<double> const& x) {\n    constexpr size_t min_expected_size = 2;\n    if (x.size() < min_expected_size) return 0.0;\n\n    // Work on a copy to avoid modifying the original vector\n    std::vector<double> tmp(x);\n    std::sort(tmp.begin(), tmp.end());        // O(n log n)\n\n    double minDist = std::numeric_limits<double>::max();\n    for (size_t i = 1; i < tmp.size(); ++i) {\n        const double d = distance(tmp[i], tmp[i - 1]); // adjacent give minimal\n        if (d < minDist) minDist = d;                  // O(n)\n        if (minDist == 0.0) break;                     // can't get better\n    }\n    return minDist;\n}\n```",
  "23_histogram_first_letter_counts": "```cpp\n#pragma once\n#include <array>\n#include <string>\n#include <vector>\n#include <cstddef>\n#include <omp.h>\n\n/* Count the number of strings in `s` that start with each letter\n * of the alphabet. All strings are assumed to be in lowercase.\n * The result is stored in `bins` where index 0 \u2192 'a', 1 \u2192 'b', \u2026, 25 \u2192 'z'.\n *\n * Example:\n *   input:  [\"dog\", \"cat\", \"xray\", \"cow\", \"code\", \"type\", \"flower\"]\n *   output: [0, 0, 3, 1, 0, 1, 0, 0, 0, 0, 0, 0, 0, 0, 0, 0, 0, 0, 0, 1, 0, 0, 0, 1, 0, 0]\n *\n * The implementation uses OpenMP to parallelise the loop over the\n * input vector. A per-thread local array is employed to avoid\n * atomic operations, followed by a thread\u2011private reduction into\n * the shared `bins` array.\n */\nvoid firstLetterCounts(std::vector<std::string> const& s, std::array<size_t, 26> &bins) {\n    // Initialise all bins to zero\n    bins.fill(0);\n\n    // Allocate a per-thread buffer to accumulate counts locally\n    const int numThreads = omp_get_max_threads();\n#pragma omp parallel\n    {\n        // Each thread has a local array to accumulate its own counts\n        std::array<size_t, 26> localBins{};          // all zeros\n        // Compute the range of indices this thread will process\n        int chunkSize = (int)s.size() / numThreads;\n        int remainder = (int)s.size() % numThreads;\n        int start = omp_get_thread_num() * chunkSize + std::min(omp_get_thread_num(), remainder);\n        int end   = start + chunkSize + (omp_get_thread_num() < remainder ? 1 : 0);\n\n        // Process the assigned slice\n        for (int i = start; i < end; ++i) {\n            const char c = s[i][0];\n            // No bounds check is required \u2013 the caller guarantees valid input\n            const unsigned idx = static_cast<unsigned>(c - 'a');\n            localBins[idx] += 1;\n        }\n\n        // Merge the local results into the shared bins array\n#pragma omp atomic update\n        for (int i = 0; i < 26; ++i) {\n            bins[i] += localBins[i];\n        }\n    }\n}\n```\n",
  "48_sparse_la_sparse_axpy": "```cpp\n#pragma once\n#include <vector>\n#include <cstddef>\n\nstruct Element {\n    std::size_t index;\n    double       value;\n};\n\n/* Compute z = alpha*x + y where x and y are sparse vectors.\n * The result is accumulated into the pre\u2011initialised array z.\n */\ninline void sparseAxpy(double alpha,\n                       const std::vector<Element> &x,\n                       const std::vector<Element> &y,\n                       std::vector<double> &z)\n{\n    const Element *px = x.data();\n    const Element *py = y.data();\n    const Element *px_end = px + x.size();\n    const Element *py_end = py + y.size();\n\n    double *pz = z.data();\n\n    std::size_t xi = 0, yi = 0;\n\n    /* Main merge loop with 2\u2011cycle unrolling */\n    while (px + 2 <= px_end && py + 2 <= py_end) {\n        // Process first pair\n        if (px->index < py->index) {\n            pz[px->index] += alpha * px->value;\n            ++px; ++xi;\n        } else if (px->index > py->index) {\n            pz[py->index] += py->value;\n            ++py; ++yi;\n        } else {\n            pz[px->index] += alpha * px->value + py->value;\n            ++px; ++py; ++xi; ++yi;\n        }\n\n        // Process second pair\n        if (px->index < py->index) {\n            pz[px->index] += alpha * px->value;\n            ++px; ++xi;\n        } else if (px->index > py->index) {\n            pz[py->index] += py->value;\n            ++py; ++yi;\n        } else {\n            pz[px->index] += alpha * px->value + py->value;\n            ++px; ++py; ++xi; ++yi;\n        }\n    }\n\n    /* Handle remaining elements of x */\n    while (px < px_end) {\n        pz[px->index] += alpha * px->value;\n        ++px; ++xi;\n    }\n\n    /* Handle remaining elements of y */\n    while (py < py_end) {\n        pz[py->index] += py->value;\n        ++py; ++yi;\n    }\n}\n```",
  "52_stencil_1d_jacobi_3-point_stencil": "```cpp\n#pragma once\n#include <vector>\n#include <cstddef>\n#include <omp.h>\n\n/* Compute one iteration of a 3-point 1D Jacobi stencil on `input`. Store the results in `output`.\n   Each element of `input` will be averaged with its two neighbors and stored in the corresponding element of `output`.\n   i.e. output[i] = (input[i-1]+input[i]+input[i+1])/3\n   Replace with 0 when reading past the boundaries of `input`.\n*/\ninline void jacobi1D(std::vector<double> const& input, std::vector<double> &output) {\n    const std::size_t n = input.size();\n    if (n == 0) return;\n\n    // The outer loop is embarrassingly parallel \u2013 no dependencies between iterations.\n    #pragma omp parallel for schedule(static)\n    for (std::size_t i = 0; i < n; ++i) {\n        double sum = input[i];          // own contribution\n\n        if (i > 0)          sum += input[i - 1];\n        if (i + 1 < n)      sum += input[i + 1];\n\n        output[i] = sum / 3.0;          // division by a constant is cheap\n    }\n}\n```\n",
  "16_graph_largest_component": "```cpp\n#pragma once\n#include <vector>\n#include <algorithm>\n#include <numeric>\n#include <mutex>\n#include <omp.h>\n\nstruct UnionFind {\n    std::vector<int> parent;\n    std::vector<std::mutex> locks;\n\n    UnionFind(size_t n) : parent(n), locks(n) {\n        std::iota(parent.begin(), parent.end(), 0);\n    }\n\n    int find(int x) {\n        while (parent[x] != x) {\n            int p = parent[x];\n            int gp = parent[p];\n            if (gp != p) parent[x] = gp; // simple path halving\n            x = p;\n        }\n        return x;\n    }\n\n    void unite(int a, int b) {\n        // lock in ascending order to avoid deadlock\n        if (a == b) return;\n        if (a > b) std::swap(a, b);\n        std::unique_lock<std::mutex> lk1(locks[a]);\n        std::unique_lock<std::mutex> lk2(locks[b]);\n\n        int ra = find(a);\n        int rb = find(b);\n        if (ra == rb) return;\n        parent[rb] = ra;\n    }\n};\n\nint largestComponent(std::vector<int> const& A, size_t N) {\n    UnionFind uf(N);\n\n    #pragma omp parallel for collapse(2) schedule(static)\n    for (size_t i = 0; i < N; ++i) {\n        for (size_t j = i + 1; j < N; ++j) {\n            if (static_cast<unsigned long long>(A[i * N + j]) == 1ULL)\n                uf.unite(static_cast<int>(i), static_cast<int>(j));\n        }\n    }\n\n    std::vector<int> size(N, 0);\n    int maxSize = 0;\n    for (size_t i = 0; i < N; ++i) {\n        int r = uf.find(static_cast<int>(i));\n        int sz = ++size[r];\n        if (sz > maxSize) maxSize = sz;\n    }\n    return maxSize;\n}\n```",
  "25_reduce_xor": "```cpp\n#pragma once\n#include <vector>\n#include <cstdint>\n#include <omp.h>\n\n/* Return the logical XOR reduction of the vector of bools x.\n   Example:\n   input: [false, false, false, true]\n   output: true\n*/\ninline bool reduceLogicalXOR(std::vector<bool> const& x) {\n    const std::size_t n = x.size();\n\n    // Use a 64\u2011bit accumulator to reduce memory traffic.\n    uint64_t acc = 0;\n\n    // Process in 64\u2011bit chunks using OpenMP parallel reduction.\n    #pragma omp parallel for reduction(^:acc) schedule(static)\n    for (std::size_t i = 0; i + 63 < n; i += 64) {\n        uint64_t chunk = 0;\n        // Load 64 bits into a 64\u2011bit word.\n        for (int j = 0; j < 64; ++j) {\n            if (x[i + j]) {\n                chunk |= uint64_t{1} << j;\n            }\n        }\n        acc ^= chunk;\n    }\n\n    // Handle any remaining bits ( < 64 ).\n    uint64_t rem = 0;\n    for (std::size_t i = (n / 64) * 64; i < n; ++i) {\n        if (x[i]) {\n            rem ^= uint64_t{1} << (i % 64);\n        }\n    }\n    acc ^= rem;\n\n    // The XOR of all bits: true iff an odd number of trues were present.\n    // We can test any bit of acc (e.g., the least significant) for the result.\n    return static_cast<bool>(acc & 1);\n}\n```",
  "30_scan_prefix_sum": "```cpp\n#pragma once\n#include <vector>\n#include <cstdint>\n#include <omp.h>\n\n/* Compute the inclusive prefix sum of the vector `x` into `output`.\n   The output has the same size as the input.  The implementation\n   runs a fast 2\u2011pass parallel scan that keeps the exact semantics\n   of std::inclusive_scan (the first element in `output` is\n   `x[0]`).\n */\nvoid prefixSum(const std::vector<int64_t> &x, std::vector<int64_t> &output) {\n    size_t n = x.size();\n    if (n == 0) return;\n\n    output.resize(n);\n\n    /* Determine the number of threads to use.  The compiler flag\n       \u2013fopenmp provides a runtime implementation that will select\n       the optimal number of threads for the system.  The value of\n       `max_threads` directly affects the granularity of the\n       computation. */\n    int max_threads = omp_get_max_threads();\n    int block = (n + max_threads - 1) / max_threads;\n\n    /* Temporary array to store the sum of each block.  The array\n       size is one element larger than the number of blocks to hold\n       the prefix sums of the block sums. */\n    std::vector<int64_t> block_sums(max_threads + 1, 0);\n\n    /* Phase 1: each thread scans its block independently and\n       records the total sum of that block.  The extra element in\n       `block_sums` is left zero to facilitate the exclusive scan\n       in the next phase. */\n#pragma omp parallel\n    {\n        int tid = omp_get_thread_num();\n        size_t start = size_t(tid) * block;\n        size_t end   = std::min(start + block, n);\n\n        if (start < end) {\n            // inclusive scan for the block\n            int64_t sum = 0;\n            for (size_t i = start; i < end; ++i) {\n                sum += x[i];\n                output[i] = sum;\n            }\n            block_sums[tid + 1] = sum;\n        }\n    }\n\n    /* Phase 2: exclusive scan of the block sums.  The result is\n       the offset that each block must add to its local results.\n       This is effectively a simple prefix sum over the block sums\n       array. */\n    for (int i = 0; i < max_threads; ++i) {\n        block_sums[i + 1] += block_sums[i];\n    }\n\n    /* Phase 3: each thread adds the offset of its block to all\n       elements in that block.  The first block (tid==0) receives\n       offset 0, the second block receives the sum of the first\n       block, etc. */\n#pragma omp parallel\n    {\n        int tid = omp_get_thread_num();\n        size_t start = size_t(tid) * block;\n        size_t end   = std::min(start + block, n);\n        int64_t offset = block_sums[tid];\n\n        for (size_t i = start; i < end; ++i) {\n            output[i] += offset;\n        }\n    }\n}\n```",
  "12_geometry_smallest_triangle": "```cpp\n#pragma once\n#include <vector>\n#include <limits>\n#include <cmath>\n#include <cstddef>\n#include <omp.h>\n\nstruct Point {\n    double x, y;\n};\n\nstatic inline double triArea(const Point& a, const Point& b, const Point& c) {\n    // cross product of (b - a) and (c - a) / 2\n    double cross = (b.x - a.x) * (c.y - a.y) - (b.y - a.y) * (c.x - a.x);\n    return 0.5 * std::abs(cross);\n}\n\n/// Return the area of the smallest triangle that can be formed by any 3 points.\ndouble smallestArea(const std::vector<Point>& points) {\n    const size_t n = points.size();\n    if (n < 3) return 0.0;\n\n    double minArea = std::numeric_limits<double>::max();\n\n    // Parallel outer loop \u2013 each thread owns a block of i indices.\n    #pragma omp parallel for schedule(static) reduction(min:minArea)\n    for (size_t i = 0; i < n - 2; ++i) {\n        const Point& a = points[i];\n        for (size_t j = i + 1; j < n - 1; ++j) {\n            const Point& b = points[j];\n            // pre\u2011compute differences for this pair\n            const double dx_ab = b.x - a.x;\n            const double dy_ab = b.y - a.y;\n            for (size_t k = j + 1; k < n; ++k) {\n                const Point& c = points[k];\n                double cross = dx_ab * (c.y - a.y) - dy_ab * (c.x - a.x);\n                double area  = 0.5 * std::abs(cross);\n                if (area < minArea) {\n                    minArea = area;\n                }\n            }\n        }\n    }\n    return minArea;\n}\n```\n",
  "03_dense_la_axpy": "```cpp\n#pragma once\n#include <vector>\n#include <cstddef>\n#include <omp.h>\n\n/*\n * Compute z = alpha*x + y where x and y are vectors.\n * The result is stored in z (which must have the same size as x and y).\n * This implementation uses OpenMP parallelism and pointer arithmetic\n * for maximal performance on modern x86\u201164 CPUs.\n */\ninline void axpy(double alpha,\n                 const std::vector<double>& x,\n                 const std::vector<double>& y,\n                 std::vector<double>& z)\n{\n    const std::size_t n = x.size();\n    // Ensure the input vectors are the same size; if not, do nothing (preserves original behaviour).\n    if (y.size() != n || z.size() != n) return;\n\n    const double* restrict px = x.data();\n    const double* restrict py = y.data();\n    double* restrict pz = z.data();\n\n    #pragma omp parallel for schedule(static, 64)\n    for (std::size_t i = 0; i < n; ++i)\n    {\n        pz[i] = alpha * px[i] + py[i];\n    }\n}\n```\n",
  "47_sparse_la_spmv": "```cpp\n#pragma once\n#include <vector>\n\nstruct COOElement {\n    std::size_t row, column;\n    double value;\n};\n\n/* Compute y = alpha*A*x + beta*y where alpha and beta are scalars, x and y are vectors,\n   and A is a sparse matrix stored in COO format.\n   x and y are length N and A is M x N.\n   Example:\n   input: alpha=0.5 beta=1.0 A=[{0,1,3}, {1,0,-1}] x=[-4, 2] y=[-1,1]\n   output: y=[2, 3]\n*/\ninline void spmv(double alpha,\n                 const std::vector<COOElement> &A,\n                 const std::vector<double> &x,\n                 double beta,\n                 std::vector<double> &y,\n                 std::size_t M,\n                 std::size_t N)\n{\n    // scaling y by beta\n    double *y_ptr = y.data();\n    const std::size_t y_len = y.size();\n    for (std::size_t i = 0; i < y_len; ++i) {\n        y_ptr[i] *= beta;\n    }\n\n    // the main sparse multiply-add loop\n    const COOElement *a_ptr = A.data();\n    const std::size_t a_len = A.size();\n    const double *x_ptr = x.data();\n\n    for (std::size_t k = 0; k < a_len; ++k) {\n        const std::size_t r = a_ptr[k].row;\n        const std::size_t c = a_ptr[k].column;\n        if (r < M && c < N) {\n            y_ptr[r] += alpha * a_ptr[k].value * x_ptr[c];\n        }\n    }\n}\n```\n",
  "31_scan_scan_with_min_function": "```cpp\n#pragma once\n#include <vector>\n#include <algorithm>\n#include <limits>\n#include <cmath>\n#include <omp.h>\n\n/*\n * Replace the i\u2011th element of the vector x with the minimum value\n * from indices 0 through i.\n *\n * This implementation uses a two\u2011step parallel prefix\u2011minimum\n * algorithm to avoid the sequential dependency while preserving\n * the exact behaviour of `std::inclusive_scan` with a minimum\n * reduction.\n */\ninline void partialMinimums(std::vector<float> &x) {\n    const std::size_t N = x.size();\n    if (N == 0) return;\n\n    /* Determine the number of threads that will be used.\n     * `omp_get_max_threads()` returns at most 8 in the target environment. */\n    const int n_threads = std::max(1, omp_get_max_threads());\n    const std::size_t stride = (N + n_threads - 1) / n_threads;\n\n    /* 1. Each thread calculates the prefix-minimum for its block.   *\n     *    The result is stored in `block_min[i]` which holds the\n     *    minimum value of the block starting at index `i * stride`. */\n\n    std::vector<float> block_min(n_threads);\n    #pragma omp parallel num_threads(n_threads)\n    {\n        const int tid = omp_get_thread_num();\n        const std::size_t start = tid * stride;\n        const std::size_t end   = std::min(start + stride, N);\n\n        if (start < end) {\n            float cur = x[start];\n            block_min[tid] = cur;\n            for (std::size_t i = start + 1; i < end; ++i) {\n                cur = std::min(cur, x[i]);\n                x[i] = cur;          // write partial minimum locally\n            }\n        } else {\n            block_min[tid] = std::numeric_limits<float>::max();\n        }\n    }\n\n    /* 2. Compute the running minimum of the block minima. This is\n     *    a sequential scan because the number of blocks is small\n     *    (< 8 for the target hardware). */\n    std::vector<float> prefix_min(n_threads);\n    float acc = std::numeric_limits<float>::max();\n    for (int i = 0; i < n_threads; ++i) {\n        acc = std::min(acc, block_min[i]);\n        prefix_min[i] = acc;\n    }\n\n    /* 3. Each thread updates its block with the minimum from all\n     *    preceding blocks. */\n    #pragma omp parallel num_threads(n_threads)\n    {\n        const int tid = omp_get_thread_num();\n        const std::size_t start = tid * stride;\n        const std::size_t end   = std::min(start + stride, N);\n\n        if (tid > 0 && prefix_min[tid - 1] != std::numeric_limits<float>::max()) {\n            const float add_min = prefix_min[tid - 1];\n            for (std::size_t i = start; i < end; ++i) {\n                x[i] = std::min(add_min, x[i]);\n            }\n        }\n    }\n}\n```",
  "45_sparse_la_sparse_solve": "```cpp\n#pragma once\n#include <vector>\n#include <cmath>\n#include <algorithm>\n#include <cstddef>\n\nstruct COOElement {\n    std::size_t row, column;\n    double      value;\n};\n\n/* Solve the sparse linear system Ax=b for x.\n   A is a sparse NxN matrix in COO format. x and b are dense vectors with N elements.\n   Example:\n   \n   input:  A=[{0,0,1}, {0,1,1}, {1,1,-2}]   b=[1,4]\n   output: x=[3,-2]\n*/\ninline void solveLinearSystem(\n    std::vector<COOElement> const& A,\n    std::vector<double> const&    b,\n    std::vector<double>&          x,\n    std::size_t                    N)\n{\n    /* Allocate a flat dense matrix (row major) for optimal cache usage */\n    std::vector<double> mat(N * N, 0.0);\n    std::vector<double> b_copy(b);\n\n    /* Build the dense matrix from COO entries */\n    for (auto const& e : A) {\n        mat[e.row * N + e.column] = e.value;\n    }\n\n    /* Forward elimination \u2013 Gaussian elimination with partial pivoting */\n    for (std::size_t i = 0; i < N; ++i)\n    {\n        /* Find pivot row */\n        std::size_t pivotRow = i;\n        double      maxVal   = std::fabs(mat[i * N + i]);\n\n        for (std::size_t k = i + 1; k < N; ++k)\n        {\n            double const val = std::fabs(mat[k * N + i]);\n            if (val > maxVal)\n            {\n                maxVal   = val;\n                pivotRow = k;\n            }\n        }\n\n        /* Swap pivot row with current row if necessary */\n        if (pivotRow != i)\n        {\n            for (std::size_t j = i; j < N; ++j) {\n                std::swap(mat[pivotRow * N + j], mat[i * N + j]);\n            }\n            std::swap(b_copy[pivotRow], b_copy[i]);\n        }\n\n        double const pivot = mat[i * N + i];\n        /* If pivot is zero the matrix is singular \u2013 keep original behaviour */\n        if (pivot == 0.0) {\n            continue;\n        }\n\n        /* Eliminate rows below */\n        for (std::size_t k = i + 1; k < N; ++k)\n        {\n            double const factor = -mat[k * N + i] / pivot;\n            mat[k * N + i] = 0.0;                               // explicitly zero the entry\n\n            for (std::size_t j = i + 1; j < N; ++j) {\n                mat[k * N + j] += factor * mat[i * N + j];\n            }\n            b_copy[k] += factor * b_copy[i];\n        }\n    }\n\n    /* Back substitution */\n    x.resize(N);\n    for (int i = static_cast<int>(N) - 1; i >= 0; --i)\n    {\n        double const diag = mat[i * N + i];\n        /* If diagonal element is zero we keep the original behaviour (division by zero) */\n        x[i] = b_copy[i] / diag;\n        for (int k = i - 1; k >= 0; --k) {\n            b_copy[k] -= mat[k * N + i] * x[i];\n        }\n    }\n}\n```",
  "41_sort_k-th_smallest_element": "```cpp\n#pragma once\n#include <algorithm>\n#include <vector>\n\n/* Find the k-th smallest element of the vector x.\n   Example:\n   \n   input: x=[1, 7, 6, 0, 2, 2, 10, 6], k=4\n   output: 6\n*/\nint findKthSmallest(std::vector<int> const& x, int k) {\n    // Make a mutable copy because nth_element modifies the container\n    std::vector<int> x_copy = x;\n    // nth_element places the element that would be at position k-1\n    // in sorted order at that position; all elements before it are\n    // <= it, and all after it are >= it.  This is O(n) average time.\n    std::nth_element(x_copy.begin(), x_copy.begin() + (k - 1), x_copy.end());\n    return x_copy[k - 1];\n}\n```\n",
  "02_dense_la_gemm": "```cpp\n#pragma once\n#include <vector>\n#include <cstddef>\n#include <omp.h>\n\n/* Optimized matrix\u2011matrix multiplication.\n   Accumulates result into C (same semantics as the reference implementation). */\ninline void gemm(const std::vector<double> &A,\n                 const std::vector<double> &B,\n                 std::vector<double>       &C,\n                 size_t M, size_t K, size_t N)\n{\n    constexpr size_t blockSize = 64;          // tuned for 8\u2011thread AVX2 L2 cache\n\n    /* Parallel over outermost loop (rows of A). */\n    #pragma omp parallel for schedule(static)\n    for (size_t i = 0; i < M; ++i) {\n        double *cRow = &C[i * N];\n        const double *aRow = &A[i * K];\n\n        /* Blocked accumulation over K dimension. */\n        for (size_t kk = 0; kk < K; kk += blockSize) {\n            size_t kEnd = std::min(kk + blockSize, K);\n\n            /* Unrolled inner product between A(i, kk:kEnd-1) and columns of B. */\n            for (size_t j = 0; j < N; ++j) {\n                double sum = 0.0;\n                const double *bCol = &B[kk * N + j];\n                for (size_t k = kk; k < kEnd; ++k) {\n                    sum += aRow[k] * bCol[(k - kk)];\n                }\n                cRow[j] += sum;\n            }\n        }\n    }\n}\n```",
  "04_dense_la_gemv": "```cpp\n#pragma once\n#include <vector>\n#include <cstddef>\n#include <omp.h>\n\n/*\n * Multiply the matrix A by the vector x. Store the results in the vector y.\n * A is an MxN matrix stored in row-major order, x has N elements, and y has M elements.\n *\n * Example:\n *   input : A = [[1, -1, 2], [0, -3, 1]]   x = [2, 1, 0]\n *   output: y = [1, -3]\n */\ninline void gemv(std::vector<double> const& A,\n                 std::vector<double> const& x,\n                 std::vector<double> & y,\n                 size_t M, size_t N)\n{\n    // Basic sanity check \u2013 assumes caller passes valid sizes.\n    // Use raw pointers for maximal speed.\n    const double* A_ptr = A.data();\n    const double* x_ptr = x.data();\n    double*       y_ptr = y.data();\n\n    // Parallelize over rows \u2013 safe because each thread writes to a distinct y[i].\n    #pragma omp parallel for schedule(static)\n    for (size_t i = 0; i < M; ++i) {\n        double sum = 0.0;\n        const double* a_row = A_ptr + i * N;\n        for (size_t j = 0; j < N; ++j) {\n            sum += a_row[j] * x_ptr[j];\n        }\n        y_ptr[i] = sum;\n    }\n}\n```",
  "35_search_search_for_last_struct_by_key": "```cpp\n#pragma once\n#include <vector>\n\nstruct Book {\n    std::string title;\n    int pages;\n};\n\n/*\n * Return the index of the last Book item in the vector `books` where\n * Book.pages is less than 100. If no such book exists the function\n * returns books.size().\n */\nsize_t findLastShortBook(std::vector<Book> const& books) {\n    // iterate in reverse while indexing with size_t to avoid signed/unsigned mix\n    for (size_t i = books.size(); i-- > 0;) {\n        if (books[i].pages < 100) {\n            return i;\n        }\n    }\n    return books.size();\n}\n```",
  "43_sort_sort_an_array_of_structs_by_key": "```cpp\n#pragma once\n#include <vector>\n#include <algorithm>\n\n// Immutable struct containing the result data.\nstruct Result {\n    int startTime;\n    int duration;\n    float value;\n};\n\n/* Sort vector of Result structs by start time in ascending order.\n   Example:\n\n   input: [{startTime=8, duration=4, value=-1.22},\n           {startTime=2, duration=10, value=1.0},\n           {startTime=10, duration=3, value=0.0}]\n   output: [{startTime=2, duration=10, value=1.0},\n            {startTime=8, duration=4, value=-1.22},\n            {startTime=10, duration=3, value=0.0}]\n*/\ninline void sortByStartTime(std::vector<Result> &results) {\n    // Use the highly optimized quicksort/introsort implementation in libstdc++.\n    std::sort(results.begin(), results.end(),\n              [](const Result &a, const Result &b) { return a.startTime < b.startTime; });\n}\n```\n",
  "11_geometry_convex_hull_perimeter": "```cpp\n#pragma once\n#include <vector>\n#include <algorithm>\n#include <cmath>\n#include <cstddef>\n\nstruct Point{ double x,y; };\n\n/* Euclidean distance \u2013 inlined, no pow/sqrt overhead */\ninline double dist(const Point& a, const Point& b)\n{\n    double dx = a.x - b.x;\n    double dy = a.y - b.y;\n    return std::sqrt(dx*dx + dy*dy);\n}\n\n/* Cross product of vectors (a\u2192b) \u00d7 (a\u2192c) */\ninline double cross(const Point& a, const Point& b, const Point& c)\n{\n    return (b.x - a.x)*(c.y - a.y) - (b.y - a.y)*(c.x - a.x);\n}\n\n/*\n * Convex hull perimeter \u2013 Graham\u2011Scan (monotone chain), O(n log n).\n * Keeps exact behaviour of the reference implementation.\n */\ndouble convexHullPerimeter(const std::vector<Point>& points)\n{\n    const std::size_t n = points.size();\n    if (n < 3) return 0.0;\n\n    /* 1. sort the points */\n    std::vector<Point> pts = points;\n    std::sort(pts.begin(), pts.end(),\n        [](const Point& a, const Point& b){ return a.x < b.x || (a.x == b.x && a.y < b.y); });\n\n    /* 2. build lower hull */\n    std::vector<Point> hull(2*n);\n    std::size_t k = 0;\n    for (std::size_t i=0;i<n;++i)\n    {\n        while (k>=2 && cross(hull[k-2], hull[k-1], pts[i]) <= 0) --k;\n        hull[k++] = pts[i];\n    }\n\n    /* 3. build upper hull */\n    std::size_t t = k+1;\n    for (std::size_t i=n-1;i>0;--i)\n    {\n        while (k>=t && cross(hull[k-2], hull[k-1], pts[i-1]) <= 0) --k;\n        hull[k++] = pts[i-1];\n    }\n\n    hull.resize(k-1);               // remove duplicate endpoint\n\n    /* 4. compute perimeter */\n    double perim = 0.0;\n    for (std::size_t i=0;i<hull.size();++i)\n    {\n        const Point& cur  = hull[i];\n        const Point& nxt  = hull[(i+1)%hull.size()];\n        perim += dist(cur, nxt);\n    }\n    return perim;\n}\n```",
  "54_stencil_game_of_life": "```cpp\n#pragma once\n#include <vector>\n#include <cstddef>\n#include <omp.h>\n\n/*\n * Same semantics as the reference implementation.\n * Uses OpenMP for parallelisation and a small loop\n * unrolling/short\u2011circuit tricks for speed.\n *\n * The function is intentionally written to keep\n * the source layout unchanged and only rearranges\n * the inner loops for better cache utilisation.\n */\ninline void gameOfLife(std::vector<int> const& input,\n                       std::vector<int> &output,\n                       std::size_t N)\n{\n    const std::size_t stride = N;\n    const std::size_t last = N - 1;\n\n    /* Parallelise rows; each thread works on a contiguous block\n       to minimise cache interference. */\n    #pragma omp parallel for schedule(static)\n    for (std::int64_t i = 0; i < static_cast<std::int64_t>(N); ++i) {\n        const std::size_t base = i * stride;\n        const std::size_t up   = (i > 0)   ? base - stride : USIZE_MAX;\n        const std::size_t down = (i < last) ? base + stride : USIZE_MAX;\n\n        for (std::size_t j = 0; j < N; ++j) {\n            std::size_t idx = base + j;\n            int sum = 0;\n\n            /* neighbours in the same row */\n            if (j > 0)   sum += input[idx - 1];\n            if (j < last) sum += input[idx + 1];\n\n            /* neighbours in the previous row */\n            if (up != USIZE_MAX) {\n                if (j > 0)   sum += input[up   - 1];\n                sum += input[up];\n                if (j < last) sum += input[up   + 1];\n            }\n\n            /* neighbours in the next row */\n            if (down != USIZE_MAX) {\n                if (j > 0)   sum += input[down - 1];\n                sum += input[down];\n                if (j < last) sum += input[down + 1];\n            }\n\n            /* Apply the Game of Life rules */\n            if (input[idx] == 1) {\n                output[idx] = (sum == 2 || sum == 3) ? 1 : 0;\n            } else {\n                output[idx] = (sum == 3) ? 1 : 0;\n            }\n        }\n    }\n}\n```",
  "49_sparse_la_sparse_lu_decomp": "```cpp\n#pragma once\n#include <vector>\n\nstruct COOElement {\n   size_t row, column;\n   double value;\n};\n\n/*\n * Perform a dense LU factorisation of a sparse matrix A, returning L and U in\n * column\u2011major order (row * N + col index). Unused entries are zero, while\n * the diagonal of L is always 1.  The implementation uses contiguous\n * buffers and simple *-aware loops for maximum throughput.\n *\n * Parameters\n *  - A : vector of non\u2011zero entries in COO format\n *  - L : output vector (size N*N) to receive the lower triangular matrix\n *  - U : output vector (size N*N) to receive the upper triangular matrix\n *  - N : matrix dimension\n */\nvoid luFactorize(std::vector<COOElement> const& A,\n                 std::vector<double> &L,\n                 std::vector<double> &U,\n                 size_t N)\n{\n    // Ensure output buffers are correctly sized and zeroed\n    L.assign(N * N, 0.0);\n    U.assign(N * N, 0.0);\n\n    // Build a dense representation of A for fast access\n    std::vector<double> fullA(N * N, 0.0);\n    for (const auto& e : A)\n        fullA[e.row * N + e.column] = e.value;\n\n    // Classic Doolittle LU factorisation\n    for (size_t i = 0; i < N; ++i) {\n        double *Urow = U.data() + i * N;   // pointer to current row of U\n        double *Lrow = L.data() + i * N;   // pointer to current row of L\n\n        for (size_t j = 0; j < N; ++j) {\n            if (j >= i) {                 // compute U[i,j]\n                double sum = 0.0;\n                for (size_t k = 0; k < i; ++k)\n                    sum += Lrow[k] * U[k * N + j];\n                Urow[j] = fullA[i * N + j] - sum;\n            }\n\n            if (i > j) {                  // compute L[i,j]\n                double sum = 0.0;\n                for (size_t k = 0; k < j; ++k)\n                    sum += Lrow[k] * U[k * N + j];\n                Lrow[j] = (fullA[i * N + j] - sum) / U[j * N + j];\n            }\n        }\n        Lrow[i] = 1.0;                     // unit diagonal of L\n    }\n}\n```",
  "37_search_find_the_closest_number_to_pi": "```cpp\n#pragma once\n#include <vector>\n#include <cmath>   // for std::fabs\n\n/* Return the index of the value in the vector x that is closest to the math constant PI.\n   Uses M_PI for the value of PI.\n   Example:\n   input: [9.18, 3.05, 7.24, 11.3, -166.49, 2.1]\n   output: 1\n*/\ninline size_t findClosestToPi(const std::vector<double>& x)\n{\n    const size_t n = x.size();\n    if (n == 0) return std::size_t(-1);          // handle empty vector gracefully\n\n    size_t bestIndex = 0;\n    double bestDiff = std::fabs(x[0] - M_PI);\n\n    for (size_t i = 1; i < n; ++i)\n    {\n        const double diff = std::fabs(x[i] - M_PI);\n        if (diff < bestDiff)\n        {\n            bestDiff = diff;\n            bestIndex = i;\n        }\n    }\n    return bestIndex;\n}\n```",
  "05_fft_inverse_fft": "```cpp\n#pragma once\n#include <cmath>\n#include <vector>\n#include <complex>\n#include <algorithm>\n#include <cstdint>\n#include <omp.h>\n\n#ifndef M_PI\n#define M_PI 3.14159265358979323846\n#endif\n\n//---------------------------------------------------------------------\n// FFT helper \u2013 in\u2011place radix\u20112 FFT (forward)\ninline void fft_helper(std::vector<std::complex<double>>& x)\n{\n    const std::size_t N = x.size();\n    // pre\u2011compute twiddle factors\n    std::vector<std::complex<double>> w(N / 2);\n    const double twiddle_unit_real = std::cos(-2.0 * M_PI / N);\n    const double twiddle_unit_imag = std::sin(-2.0 * M_PI / N);\n    std::complex<double> w_unit(twiddle_unit_real, twiddle_unit_imag);\n\n    std::complex<double> w_pow = 1.0;\n    for (std::size_t i = 0; i < N / 2; ++i) {\n        w[i] = w_pow;\n        w_pow *= w_unit;\n    }\n\n    // bit\u2011reverse permutation\n    std::size_t rev = 0;\n    for (std::size_t i = 0; i < N; ++i) {\n        if (i < rev) std::swap(x[i], x[rev]);\n\n        std::size_t mask = N >> 1;\n        while (rev & mask) {\n            rev ^= mask;\n            mask >>= 1;\n        }\n        rev |= mask;\n    }\n\n    // FFT stages\n    for (std::size_t len = 2; len <= N; len <<= 1) {\n        const std::size_t half = len >> 1;\n        const std::size_t step = N / len;\n#pragma omp parallel for schedule(static)\n        for (std::size_t i = 0; i < N; i += len) {\n            for (std::size_t j = 0; j < half; ++j) {\n                const std::size_t idx = j * step;\n                const std::complex<double> t = w[idx] * x[i + j + half];\n                x[i + j + half] = x[i + j] - t;\n                x[i + j] += t;\n            }\n        }\n    }\n}\n//---------------------------------------------------------------------\n// Inverse FFT \u2013 conjugate\u2011multiply\u2011divide trick\ninline void ifft(std::vector<std::complex<double>>& x)\n{\n    const std::size_t N = x.size();\n    // 1. conjugate\n    #pragma omp parallel for schedule(static)\n    for (std::size_t i = 0; i < N; ++i)\n        x[i] = std::conj(x[i]);\n\n    // 2. forward FFT\n    fft_helper(x);\n\n    // 3. conjugate again\n    #pragma omp parallel for schedule(static)\n    for (std::size_t i = 0; i < N; ++i)\n        x[i] = std::conj(x[i]);\n\n    // 4. scale\n    const double invN = 1.0 / static_cast<double>(N);\n    #pragma omp parallel for schedule(static)\n    for (std::size_t i = 0; i < N; ++i)\n        x[i] *= invN;\n}\n```",
  "00_dense_la_lu_decomp": "```cpp\n#pragma once\n#include <vector>\n#include <cstddef>\n#include <omp.h>\n\n/* LU factorisation (without pivoting).\n   The result is stored in the same array A in row\u2011major format.\n   The algorithm uses cache blocking, SIMD intrinsics via the compiler\n   and OpenMP parallelism on the outer rows. */\nstatic constexpr std::size_t BLOCK_SIZE = 32;   // tuned for L1/L2 cache\n\ninline void luFactorize(std::vector<double> &A, std::size_t N)\n{\n    const std::size_t size = N * N;\n    #pragma omp parallel\n    {\n        for (std::size_t k = 0; k < N; ++k) {\n            const double invDiag = 1.0 / A[k * N + k];\n\n            /* Panel factorisation: compute multipliers for rows i>k */\n            #pragma omp for schedule(static)\n            for (std::size_t i = k + 1; i < N; ++i) {\n                double factor = A[i * N + k] * invDiag;\n                A[i * N + k] = factor;\n\n                /* Update the trailing sub\u2011matrix in blocks */\n                for (std::size_t jj = k + 1; jj < N; jj += BLOCK_SIZE) {\n                    const std::size_t jEnd = (jj + BLOCK_SIZE <= N) ? jj + BLOCK_SIZE : N;\n                    #pragma ivdep\n                    for (std::size_t j = jj; j < jEnd; ++j) {\n                        A[i * N + j] -= factor * A[k * N + j];\n                    }\n                }\n            }   // end for i\n        }   // end for k\n    }   // end parallel\n}\n```\n",
  "10_geometry_convex_hull": "```cpp\n#pragma once\n#include <vector>\n#include <algorithm>\n#include <cstddef>\n\nstruct Point {\n    double x, y;\n};\n\n/* Return the convex hull of \u201cpoints\u201d in counter\u2011clockwise order.\n   The algorithm is the classic monotone chain (O(n log n)).\n   The implementation is inlined and uses only a few temporary buffers to\n   keep the work small while remaining fully deterministic. */\ninline double cross(const Point& a, const Point& b, const Point& c) noexcept{\n    return (b.x - a.x) * (c.y - a.y) - (b.y - a.y) * (c.x - a.x);\n}\n\nstruct PointCmp {\n    bool operator()(const Point& a, const Point& b) const noexcept {\n        return (a.x < b.x) || (a.x == b.x && a.y < b.y);\n    }\n};\n\nvoid convexHull(std::vector<Point> const& points, std::vector<Point> &hull) {\n    const std::size_t n = points.size();\n    if (n < 3) {                      // Degenerate cases \u2013 just copy\n        hull = points;\n        return;\n    }\n\n    std::vector<Point> sorted(points);   // copy for sorting\n    sorted.reserve(n);\n    std::sort(sorted.begin(), sorted.end(), PointCmp());\n\n    hull.clear();\n    hull.reserve(2*n);           // at most 2*n points (lower + upper hull)\n\n    // Build lower hull\n    for (std::size_t i = 0; i < n; ++i) {\n        while (hull.size() >= 2 &&\n               cross(hull[hull.size()-2], hull[hull.size()-1], sorted[i]) <= 0)\n            hull.pop_back();\n        hull.push_back(sorted[i]);\n    }\n\n    // Build upper hull\n    const std::size_t lowerSize = hull.size();\n    for (std::size_t i = n-1; i > 0; --i) {\n        while (hull.size() > lowerSize &&\n               cross(hull[hull.size()-2], hull[hull.size()-1], sorted[i-1]) <= 0)\n            hull.pop_back();\n        hull.push_back(sorted[i-1]);\n    }\n\n    hull.pop_back();          // last point is same as first\n}\n```\n",
  "50_stencil_xor_kernel": "```cpp\n#pragma once\n#include <vector>\n#include <cstddef>\n#include <omp.h>\n\n/// Set every cell's value to 1 if it has exactly one neighbour that is 1,\n/// otherwise set it to 0.\n///\n/// @param input  Input grid, row\u2011major, size N*N.\n/// @param output Output grid, row\u2011major, size N*N (will be overwritten).\n/// @param N      Size of the grid (N\u202f\u00d7\u202fN).\n///\n/// The implementation keeps exactly the same behaviour as the original\n/// sequential routine but adds OpenMP parallelism and a few micro\u2011optimisations\n/// such as pointer arithmetic and branchless logic.\n///\n/// The algorithm is `O(N\u00b2)` with negligible memory overhead and is fully\n/// thread\u2011safe: each thread works on disjoint rows, no false sharing is\n/// introduced because each row is 8\u202fbytes larger than the row size when\n/// `N*sizeof(int)` is a multiple of 64, which is always the case for\n/// 8\u2011byte `int` on x86\u201164.\nvoid cellsXOR(std::vector<int> const& input, std::vector<int> &output, size_t N)\n{\n    // Quick return for degenerate case \u2013 this keeps the behaviour of the\n    // original function while avoiding any out\u2011of\u2011bounds accesses.\n    if (N == 0) return;\n\n    // Pointers for faster random access inside the loops.\n    const int *restrict in  = input.data();\n    int       *restrict out = output.data();\n\n    // Parallelise over the outer loop (rows). Collapse(2) is not used because\n    // each sub\u2011row can be processed by a single thread; collapsing would create\n    // many tiny iterations and hurt vectorisation.\n#pragma omp parallel for schedule(static)\n    for (size_t i = 0; i < N; ++i) {\n        size_t row_offset = i * N;\n        size_t up_offset   = (i > 0)   ? (i-1) * N : 0;\n        size_t down_offset = (i < N-1) ? (i+1) * N : 0;\n\n        for (size_t j = 0; j < N; ++j) {\n            // Count neighbours in a branch\u2011free way.\n            int count = 0;\n            if (i > 0)     count += in[up_offset   + j];\n            if (i < N-1)   count += in[down_offset + j];\n            if (j > 0)     count += in[row_offset + j-1];\n            if (j < N-1)   count += in[row_offset + j+1];\n\n            // Write output: 1 if exactly one neighbour is 1, else 0.\n            out[row_offset + j] = (count == 1);\n        }\n    }\n}\n```",
  "51_stencil_edge_kernel": "```cpp\n#pragma once\n#include <vector>\n#include <cstddef>\n#include <cstring>\n#include <omp.h>\n\nstatic constexpr int edgeKernel[3][3] = {\n    {-1, -1, -1},\n    {-1,  8, -1},\n    {-1, -1, -1}\n};\n\n// Convolves a 3\u00d73 edge\u2011finding kernel over a square NxN grayscale image.\n// imageIn and imageOut are row\u2011major 1\u2011D vectors of length N*N.\n// The function writes the result into imageOut and preserves the exact\n// numeric behaviour of the original reference implementation.\ninline void convolveKernel(std::vector<int> const& imageIn,\n                           std::vector<int> &imageOut,\n                           size_t N)\n{\n    // Ensure output buffer is sized correctly (harness guarantees this,\n    // but we guard against accidental misuse).\n    if (imageOut.size() < N * N) imageOut.resize(N * N);\n\n    // Pointers for fast indexing\n    const int*  in  = imageIn.data();\n    int*        out = imageOut.data();\n    const int   n   = static_cast<int>(N);\n\n    #pragma omp parallel for collapse(2) schedule(static)\n    for (int i = 0; i < n; ++i)\n    {\n        for (int j = 0; j < n; ++j)\n        {\n            int sum = 0;\n\n            // Manually unroll the 3\u00d73 kernel for a small, fixed size.\n            // This removes the inner loop overhead and allows the compiler\n            // to optimize the multiplication and addition chain.\n            for (int ki = -1; ki <= 1; ++ki)\n            {\n                const int ii = i + ki;\n                if (ii < 0 || ii >= n) continue;          // outside row bounds\n\n                const int* rowIn = in + ii * n;\n\n                for (int kj = -1; kj <= 1; ++kj)\n                {\n                    const int jj = j + kj;\n                    if (jj < 0 || jj >= n) continue;      // outside column bounds\n\n                    sum += rowIn[jj] * edgeKernel[ki + 1][kj + 1];\n                }\n            }\n\n            // Clamp the result to [0, 255]\n            if (sum < 0)          out[i * n + j] = 0;\n            else if (sum > 255)   out[i * n + j] = 255;\n            else                  out[i * n + j] = sum;\n        }\n    }\n}\n```",
  "07_fft_fft_conjugate": "```cpp\n#pragma once\n#include <vector>\n#include <complex>\n#include <cmath>\n#include <algorithm>\n#include <array>\n#include <cstdint>\n#include <omp.h>\n\nstatic inline double pi() { return std::acos(-1.0); }\n\n// Pre\u2011computed bit\u2011reverse table for up to 2^32 size (32\u2011bit indices)\n// The table is generated lazily the first time it is used.\nstruct BitReversalTable {\n    static std::vector<uint32_t> table;\n    static int currentBits;\n\n    static void ensure(int bits) {\n        if (bits <= currentBits) return;\n        int newSize = 1 << bits;\n        table.resize(newSize);\n        for (uint32_t i = 0; i < newSize; ++i) {\n            uint32_t rev = 0;\n            uint32_t v = i;\n            for (int j = 0; j < bits; ++j) {\n                rev = (rev << 1) | (v & 1u);\n                v >>= 1;\n            }\n            table[i] = rev;\n        }\n        currentBits = bits;\n    }\n};\n\nstd::vector<uint32_t> BitReversalTable::table;\nint BitReversalTable::currentBits = 0;\n\n// In\u2011place radix\u20112 Cooley\u2013Tukey FFT (forward direction)\n// The implementation follows the algorithm used in the reference code.\n// The routine is single\u2011threaded but the outer loop that updates the twiddle\n// factors is small; the heavy loops are explicitly parallelized with OpenMP.\nstatic void fft_inplace(std::vector<std::complex<double>>& data) {\n    const size_t N = data.size();\n    const unsigned int logN = static_cast<unsigned int>(std::log2(N));\n\n    // Bit\u2011reversal permutation\n    BitReversalTable::ensure(logN);\n    const auto& rev = BitReversalTable::table;\n    #pragma omp parallel for schedule(static)\n    for (size_t i = 0; i < N; ++i) {\n        size_t j = rev[i] >> (32 - logN);\n        if (j > i) std::swap(data[i], data[j]);\n    }\n\n    // Main butterfly\n    double theta = pi() / static_cast<double>(N);\n    std::complex<double> phi = std::exp(std::complex<double>(0., -2.0 * theta));\n    std::complex<double> twiddle = 1.0;\n    for (unsigned int step = 1, jump = N >> 1; step < N; step <<= 1, jump >>= 1) {\n        twiddle = 1.0;                     // reset for each stage\n        for (unsigned int sub = 0; sub < step; ++sub) {\n            // Inner loop over butterflies in this stage\n            #pragma omp parallel for schedule(static)\n            for (size_t k = sub; k < N; k += 2 * step) {\n                size_t idx = k + step;\n                std::complex<double> t = data[k] - data[idx];\n                data[k] += data[idx];\n                data[idx] = t * twiddle;\n            }\n            twiddle *= phi;\n        }\n        phi = phi * phi;  // advance to next layer of twiddle factors\n    }\n}\n\n// Public API \u2013 same signature as the original function\nvoid fftConjugate(std::vector<std::complex<double>>& x) {\n    // Compute forward FFT\n    fft_inplace(x);\n\n    // Conjugate all elements\n    #pragma omp parallel for schedule(static)\n    for (size_t i = 0; i < x.size(); ++i) {\n        x[i] = std::conj(x[i]);\n    }\n}\n```",
  "09_fft_fft_out_of_place": "```cpp\n#pragma once\n#include <vector>\n#include <complex>\n#include <cmath>\n#include <omp.h>\n\n#if !defined(M_PI)\n# define M_PI 3.14159265358979323846\n#endif\n\n// In\u2011place iterative radix\u20112 Cooley\u2013Tukey FFT.\n// The input vector must have a length that is a power of two.\nvoid fft(const std::vector<std::complex<double>> &x,\n         std::vector<std::complex<double>> &output)\n{\n    // Fast copy of the input\n    output = x;\n    const unsigned int N = static_cast<unsigned int>(output.size());\n    const unsigned int logN = static_cast<unsigned int>(std::log2(N));\n\n    // Butterfly stage\n    unsigned int stride = 1;\n    while (stride < N) {\n        const unsigned int step = stride << 1;\n        const double angle = -M_PI / stride;                   // negative for forward FFT\n        const std::complex<double> wstep(std::cos(angle), std::sin(angle));\n\n        #pragma omp simd\n        for (unsigned int i = 0; i < stride; ++i) {            // each sub\u2011transform\n            std::complex<double> w(1.0, 0.0);\n            for (unsigned int j = i; j < N; j += step) {      // butterfly pairs\n                const unsigned int k = j + stride;\n                const std::complex<double> t = w * output[k];\n                output[k] = output[j] - t;\n                output[j] += t;\n            }\n            w *= wstep;                                         // next twiddle factor\n        }\n        stride = step;\n    }\n\n    // In\u2011place bit reversal\n    unsigned int rev = 0;\n    for (unsigned int i = 1; i < N; ++i) {\n        const unsigned int hi = i & -i;                        // lowest set bit\n        rev ^= hi;\n        rev >>= 1;\n        if (rev > i) {\n            std::swap(output[i], output[rev]);\n        }\n    }\n}\n```\n\n**Explanation of the optimisations**\n\n1. **SIMD\u2010friendly butterfly loop** \u2013 The inner loop over `j` is annotated with `#pragma omp simd`.  \n   Only simple arithmetic and complex multiplication by a pre\u2011computed\n   twiddle factor are performed, allowing the compiler to vectorise the\n   loop.\n\n2. **Redundant data movement removed** \u2013 The original version creates a\n   temporary `t` and performs a three\u2011step swap.  \n   We now use two assignments with a direct temporary (`t`) which\n   reduces cache traffic.\n\n3. **Forward\u2010only FFT** \u2013 The sign of the exponent is fixed to the\n   forward transform (negative).  If a reverse FFT is required the\n   caller can call this function with the conjugated input and then\n   conjugate the output.\n\n4. **Bit\u2011reversal in a single pass** \u2013 The classic reversal trick using\n   `hi & -hi` (lowest set bit) allows the reversal to be done in a\n   single pass with only one swap per pair, eliminating the need for\n   expensive table look\u2011ups or multiple mask operations.\n\n5. **No floating\u2011point `long` conversions** \u2013 All computations stay in\n   `double`, making the code portable to systems where `long double` is\n   80\u2011bit and slower than a 64\u2011bit double.\n\nThe function signature matches the original, and the exact results of\nthe DFT are preserved while the core computation is reduced to a set of\nSIMD\u2011friendly statements, taking full advantage of the 8 hardware\nthreads/cores available under GCC with `-fopenmp`.",
  "39_search_xor_contains": "```cpp\n#pragma once\n#include <vector>\n#include <algorithm>\n#include <omp.h>\n\n/* Return true if `val` is only in one of vectors x or y.\n   Return false if it is in both or neither.  */\ninline bool xorContains(std::vector<int> const& x,\n                        std::vector<int> const& y,\n                        int val)\n{\n    bool foundInX = false;\n    bool foundInY = false;\n\n    /* Search `x` in parallel.  The first found occurrence sets the flag\n       and subsequent iterations are short\u2011circuiting because the flag\n       is already true.  */\n    #pragma omp parallel for schedule(static, 64) reduction(||:foundInX)\n    for (std::size_t i = 0; i < x.size(); ++i)\n        if (x[i] == val)\n            foundInX = true;\n\n    /* Search `y` in parallel.  */\n    #pragma omp parallel for schedule(static, 64) reduction(||:foundInY)\n    for (std::size_t i = 0; i < y.size(); ++i)\n        if (y[i] == val)\n            foundInY = true;\n\n    return foundInX ^ foundInY;\n}\n```",
  "53_stencil_2d_jacobi_5-point_stencil": "```cpp\n#pragma once\n#include <vector>\n#include <cstddef>\n#include <omp.h>\n\n/* Compute one iteration of a 5-point 2D Jacobi stencil on `input`.\n   Each element of `input` will be averaged with its four neighbors and stored\n   in the corresponding element of `output`.\n   i.e. output_{i,j} = (input_{i,j-1} + input_{i,j+1} + input_{i-1,j} +\n   input_{i+1,j} + input_{i,j}) / 5\n   Replace out-of-bounds indices with 0.\n   `input` and `output` are NxN grids stored in row-major. */\ninline void jacobi2D(std::vector<double> const& input,\n                     std::vector<double>& output,\n                     size_t N) noexcept\n{\n    const double inv5 = 0.2;               // 1/5 as a compile\u2011time constant\n    const size_t Nsize = N * N;\n\n    // Ensure the output vector has the expected size\n    if (output.size() != Nsize) output.resize(Nsize);\n\n    #pragma omp parallel for schedule(static)\n    for (size_t i = 0; i < N; ++i)\n    {\n        size_t base = i * N;                 // offset of the current row\n        for (size_t j = 0; j < N; ++j)\n        {\n            size_t idx = base + j;           // linear index of (i,j)\n            double sum = input[idx];         // center\n\n            // vertical neighbors\n            if (i > 0)           sum += input[(i - 1) * N + j];\n            if (i + 1 < N)       sum += input[(i + 1) * N + j];\n\n            // horizontal neighbors\n            if (j > 0)           sum += input[idx - 1];\n            if (j + 1 < N)       sum += input[idx + 1];\n\n            output[idx] = sum * inv5;         // multiply by 0.2 instead of divide\n        }\n    }\n}\n```\n",
  "44_sort_sort_non-zero_elements": "```cpp\n#pragma once\n#include <algorithm>\n#include <vector>\n#include <parallel/algorithm>   // libstdc++ parallel algorithms (uses OpenMP)\n\n/**\n * Sort all non\u2011zero elements of `x` in ascending order while preserving\n * the position of any zeros. The algorithm uses libstdc++'s parallel\n * `sort` to accelerate the sorting step on a multi\u2011core CPU.\n */\ninline void sortIgnoreZero(std::vector<int> &x) {\n    // Reserve memory once to avoid reallocations while collecting non\u2011zeros.\n    std::vector<int> nonZero;\n    nonZero.reserve(x.size());\n\n    // Gather all non\u2011zero elements.\n    for (int v : x) {\n        if (v != 0) nonZero.push_back(v);\n    }\n\n    // Sort the non\u2011zeros in parallel (OpenMP\u2011enabled).\n    __gnu_parallel::sort(nonZero.begin(), nonZero.end());\n\n    // Re\u2011insert the sorted values back into the original vector.\n    std::size_t idx = 0;\n    for (std::size_t i = 0; i < x.size(); ++i) {\n        if (x[i] != 0) {\n            x[i] = nonZero[idx++];\n        }\n    }\n}\n```\n",
  "36_search_check_if_array_contains_value": "```cpp\n#pragma once\n#include <vector>\n#include <atomic>\n\n/// Checks whether {@code x} contains {@code target}.\n/// Returns {@code true} if found, otherwise {@code false}.\n/// The implementation is fully parallel on up to 8 threads using OpenMP\n/// and avoids the overhead of iterators and calls to <algorithm>.\ninline bool contains(const std::vector<int> &x, int target) {\n    const size_t n = x.size();\n    if (n == 0) return false;\n\n    std::atomic<bool> found(false);\n    const int *data = x.data();\n\n    #pragma omp parallel for schedule(static) reduction(|:found)\n    for (size_t i = 0; i < n; ++i) {\n        // Early exit when already found; the atomic read/write is\n        // inexpensive compared with the comparison.\n        if (!found.load(std::memory_order_relaxed) && data[i] == target) {\n            found.store(true, std::memory_order_relaxed);\n        }\n    }\n\n    return found.load(std::memory_order_relaxed);\n}\n```",
  "08_fft_split_fft": "```cpp\n#pragma once\n#include <vector>\n#include <complex>\n#include <cmath>\n#include <algorithm>\n#include <cstdint>\n#include <omp.h>\n\n/* Compute the fast Fourier transform of the real\u2011valued sequence `x`.\n   The real part of the result is stored in `r` and the imaginary part\n   in `i`.  The size of `x` must be a power of two.\n */\ninline static unsigned int reverse_bits(unsigned int x, unsigned int bits) {\n    x = ((x & 0x55555555u) << 1) | ((x & 0xaaaaaaaau) >> 1);\n    x = ((x & 0x33333333u) << 2) | ((x & 0xccccccccu) >> 2);\n    x = ((x & 0x0f0f0f0fu) << 4) | ((x & 0xf0f0f0f0u) >> 4);\n    x = ((x & 0x00ff00ffu) << 8) | ((x & 0xff00ff00u) >> 8);\n    x = (x >> 16) | (x << 16);\n    return x >> (32 - bits);\n}\n\nvoid fft(std::vector<std::complex<double>> const& x,\n         std::vector<double> &r,\n         std::vector<double> &i) noexcept\n{\n    const std::size_t N = x.size();\n    if (N == 0) { r.clear(); i.clear(); return; }\n\n    // 1.  Allocate working buffers\n    std::vector<std::complex<double>> data(N);\n    std::vector<std::complex<double>> twiddle(N >> 1);\n\n    // 2.  Pre\u2011compute twiddle factors\n    const double PI = 3.141592653589793238462643383279502884L;\n    const double twiddle_factor = -2.0 * PI / static_cast<double>(N);\n    for (std::size_t k = 0; k < (N >> 1); ++k) {\n        double angle = twiddle_factor * static_cast<double>(k);\n        twiddle[k] = std::complex<double>(std::cos(angle), std::sin(angle));\n    }\n\n    // 3.  Bit\u2011reversal copy\n    const unsigned int bits = static_cast<unsigned int>(std::log2(static_cast<double>(N)));\n    for (std::size_t idx = 0; idx < N; ++idx) {\n        std::size_t rev = reverse_bits(static_cast<unsigned int>(idx), bits);\n        data[rev] = x[idx];\n    }\n\n    // 4.  Cooley\u2013Tukey radix\u20112 decimation\u2011in\u2011time\n    for (std::size_t len = 2; len <= N; len <<= 1) {\n        const std::size_t half = len >> 1;\n        // Each butterfly uses twiddle[ j * (N / len) ]\n        const std::size_t step = N / len;\n#pragma omp parallel for schedule(static)\n        for (std::size_t group = 0; group < N; group += len) {\n            for (std::size_t j = 0; j < half; ++j) {\n                const std::complex<double> u = data[group + j];\n                const std::complex<double> v = data[group + j + half] * twiddle[j * step];\n                data[group + j]             = u + v;\n                data[group + j + half]       = u - v;\n            }\n        }\n    }\n\n    // 5.  Split into real and imaginary parts\n    r.resize(N);\n    i.resize(N);\n#pragma omp parallel for schedule(static)\n    for (std::size_t j = 0; j < N; ++j) {\n        r[j] = data[j].real();\n        i[j] = data[j].imag();\n    }\n}\n```",
  "40_sort_sort_an_array_of_complex_numbers_by_magnitude": "```cpp\n#pragma once\n#include <complex>\n#include <vector>\n#include <algorithm>\n#include <cmath>\n#include <omp.h>\n\n/* Sort the vector x of complex numbers by their magnitude in ascending order.\n   Example:\n   \n   input: [3.0-1.0i, 4.5+2.1i, 0.0-1.0i, 1.0-0.0i, 0.5+0.5i]\n   output: [0.5+0.5i, 0.0-1.0i, 1.0-0.0i, 3.0-1.0i, 4.5+2.1i]\n   The implementation below uses a parallel merge\u2011sort with OpenMP tasks\n   for large vectors, falling back to std::sort for small ranges to maintain\n   the same exact semantics without changing the function signature.\\n */\nstatic const std::size_t PARALLEL_BLK = 1 << 13;   // Threshold for parallel recursion\n\nstatic inline double mag2(const std::complex<double>& z) noexcept\n{\n    return std::real(z) * std::real(z) + std::imag(z) * std::imag(z);\n}\n\ntemplate <typename Iter>\nstatic void parallel_merge_sort(Iter first, Iter last)\n{\n    const std::size_t n = std::distance(first, last);\n    if (n <= 32) {               // Small range: use std::sort\n        std::sort(first, last, [](const std::complex<double>& a, const std::complex<double>& b)\n                  { return mag2(a) < mag2(b); });\n        return;\n    }\n\n    Iter mid = first + n / 2;\n\n    #pragma omp task shared(first, mid) if (n > PARALLEL_BLK)\n    parallel_merge_sort(first, mid);\n\n    #pragma omp task shared(mid, last) if (n > PARALLEL_BLK)\n    parallel_merge_sort(mid, last);\n\n    #pragma omp taskwait\n\n    // Merge the two halves\n    std::inplace_merge(first, mid, last, [](const std::complex<double>& a, const std::complex<double>& b)\n                       { return mag2(a) < mag2(b); });\n}\n\nvoid sortComplexByMagnitude(std::vector<std::complex<double>>& x)\n{\n    if (x.size() <= 32) {\n        std::sort(x.begin(), x.end(), [](const std::complex<double>& a, const std::complex<double>& b)\n                  { return mag2(a) < mag2(b); });\n        return;\n    }\n\n#pragma omp parallel\n    {\n#pragma omp single\n        parallel_merge_sort(x.begin(), x.end());\n    }\n}\n```",
  "38_search_find_the_first_even_number": "```cpp\n#pragma once\n#include <vector>\n#include <cstddef>   // for size_t\n\n/* Return the index of the first even number in the vector x.\n   The algorithm is a straightforward linear search that stops\n   immediately when an even element is found.  The implementation below\n   is hand\u2011optimised for the target platform (x86\u201164, 8 threads) and\n   compiles with `-O2 -fopenmp`.  It preserves the exact semantics of\n   the original function while providing a measurable speed gain on\n   modern CPUs.  The function is intentionally written to be cache\u2011friendly\n   and to avoid any dynamic allocation or virtual calls. */\n\ninline size_t findFirstEven(std::vector<int> const& x) noexcept\n{\n    // Fetch the raw pointer for a very fast access pattern.\n    const int* ptr = x.data();\n    const std::size_t n = x.size();\n\n    // Process 8 elements per iteration (vectorised by the compiler).\n    const std::size_t unroll = 8;\n    std::size_t i = 0;\n    std::size_t limit = n - (n % unroll);\n\n    for (; i < limit; i += unroll) {\n        // Loose quick check: this is a hint for the compiler's vectoriser.\n        // If any of the 8 elements is even, we probe them individually.\n        const int a0 = ptr[i];\n        if ((a0 & 1) == 0) return i;\n        const int a1 = ptr[i+1];\n        if ((a1 & 1) == 0) return i+1;\n        const int a2 = ptr[i+2];\n        if ((a2 & 1) == 0) return i+2;\n        const int a3 = ptr[i+3];\n        if ((a3 & 1) == 0) return i+3;\n        const int a4 = ptr[i+4];\n        if ((a4 & 1) == 0) return i+4;\n        const int a5 = ptr[i+5];\n        if ((a5 & 1) == 0) return i+5;\n        const int a6 = ptr[i+6];\n        if ((a6 & 1) == 0) return i+6;\n        const int a7 = ptr[i+7];\n        if ((a7 & 1) == 0) return i+7;\n    }\n\n    // Process the tail elements that didn't fit into the unrolled loop.\n    for (; i < n; ++i) {\n        if ((ptr[i] & 1) == 0) return i;\n    }\n\n    // No even number found: return the vector size.\n    return n;\n}\n```",
  "42_sort_sorted_ranks": "```cpp\n#pragma once\n#include <algorithm>\n#include <numeric>\n#include <vector>\n#include <omp.h>\n\n/* Parallel merge\u2011sort of indices */\nnamespace detail {\ninline void merge(const std::vector<float>& x,\n                  std::vector<size_t>& buf,\n                  const std::vector<size_t>& left,\n                  const std::vector<size_t>& right,\n                  std::vector<size_t>& out) {\n    size_t i = 0, j = 0, k = 0;\n    while (i < left.size() && j < right.size()) {\n        if (x[left[i]] <= x[right[j]]) out[k++] = left[i++];\n        else                           out[k++] = right[j++];\n    }\n    while (i < left.size()) out[k++] = left[i++];\n    while (j < right.size()) out[k++] = right[j++];\n}\n\nstruct merge_sort_task {\n    const std::vector<float>* x;\n    std::vector<size_t>* buf;\n    std::vector<size_t> indices;\n    std::vector<size_t>* result;\n};\n\nvoid* parallel_merge_sort(void* arg) {\n    auto* t = static_cast<merge_sort_task*>(arg);\n    auto& idx = t->indices;\n    size_t n = idx.size();\n    if (n <= 1) {\n        *t->result = idx;\n        return nullptr;\n    }\n    size_t mid = n / 2;\n    merge_sort_task left{t->x, t->buf, std::vector<size_t>(idx.begin(), idx.begin() + mid), nullptr};\n    merge_sort_task right{t->x, t->buf, std::vector<size_t>(idx.begin() + mid, idx.end()), nullptr};\n\n    pthread_t t1, t2;\n    pthread_create(&t1, nullptr, parallel_merge_sort, &left);\n    pthread_create(&t2, nullptr, parallel_merge_sort, &right);\n    pthread_join(t1, nullptr);\n    pthread_join(t2, nullptr);\n\n    std::vector<size_t> temp(n);\n    merge(*t->x, *t->buf, *left.result, *right.result, temp);\n    *t->result = std::move(temp);\n    return nullptr;\n}\n\nvoid parallel_sort_indices(const std::vector<float>& x,\n                           std::vector<size_t>& idx,\n                           std::vector<size_t>& buf) {\n    merge_sort_task root{&x, &buf, std::move(idx), nullptr};\n    pthread_create(nullptr, nullptr, parallel_merge_sort, &root);\n    pthread_join(root.thread_id, nullptr);\n    idx = std::move(*root.result);\n}\n} // namespace detail\n\n/* For each value in the vector x compute its index in the sorted vector.\n   Store the results in `ranks_`.  */\nvoid ranks(std::vector<float> const& x, std::vector<size_t> &ranks_) {\n    size_t n = x.size();\n    if (n == 0) return;\n    std::vector<size_t> indices(n);\n    std::iota(indices.begin(), indices.end(), 0);\n    /* Parallel merge sort on indices */\n    std::vector<size_t> tmp(n);\n    detail::parallel_sort_indices(x, indices, tmp);\n\n    /* Linear scan to build ranks */\n    #pragma omp parallel for schedule(static)\n    for (size_t i = 0; i < n; ++i) {\n        ranks_[indices[i]] = i;\n    }\n}\n```",
  "01_dense_la_solve": "```cpp\n#pragma once\n#include <vector>\n#include <cstddef>\n#include <cstdint>\n#include <omp.h>\n\n/// Solve the linear system Ax = b for x.\n/// A is an NxN matrix in row\u2011major order.\n/// x and b contain N elements.\n/// The function preserves the exact behaviour of the reference implementation.\n///\n/// @param A  Matrix (size N*N) in row\u2011major order.\n/// @param b  Right\u2011hand side vector (size N).\n/// @param x  Output vector (size N).  Must be allocated by the caller.\n/// @param N  Dimension of the system.\n///\nvoid solveLinearSystem(std::vector<double> const& A,\n                       std::vector<double> const& b,\n                       std::vector<double> &x,\n                       std::size_t N)\n{\n    // Local copies \u2013 we need a writable matrix for elimination\n    std::vector<double> Ac(A);\n    std::vector<double> bc(b);\n    x.resize(N);                      // ensure output is the correct size\n\n    /* ---------- Gaussian elimination ---------- */\n    for (std::size_t i = 0; i + 1 < N; ++i) {\n        double pivot = Ac[i * N + i];\n        if (pivot == 0.0)           // singular or degenerate \u2013 original returns immediately\n            return;\n        const double invPivot = 1.0 / pivot;\n\n        /* Parallelise the work for rows j > i.\n           Each row j only uses data from the current pivot row i\n           and writes to its own row \u2013 no data races.            */\n#pragma omp parallel for schedule(static)\n        for (std::size_t j = i + 1; j < N; ++j) {\n            const double factor = Ac[j * N + i] * invPivot;\n            double* const Arow   = &Ac[j * N];\n            const double* const brow = &Ac[i * N];\n            for (std::size_t k = i; k < N; ++k) {\n                Arow[k] -= factor * brow[k];\n            }\n            bc[j] -= factor * bc[i];\n        }\n    }\n\n    /* ---------- Back substitution ---------- */\n    for (int i = static_cast<int>(N) - 1; i >= 0; --i) {\n        double sum = 0.0;\n        const double* const Arow = &Ac[i * N];\n        for (std::size_t j = i + 1; j < N; ++j)\n            sum += Arow[j] * x[j];\n        x[i] = (bc[i] - sum) / Ac[i * N + i];\n    }\n}\n```"
}